[
     {
         "title": "This Program Rescued Army Recruiting",
         "description": "The defense secretary cites a ‘Trump bump.’ But the Army’s recruiting surge wouldn’t have been possible without the program started three years ago at Fort Jackson.",
         "link": "https://www.nytimes.com/2025/10/04/us/politics/army-recruiting-trump.html",
         "links": [
             "https://www.nytimes.com/2025/10/04/us/politics/army-recruiting-trump.html"
         ],
         "published": "Sat, 04 Oct 2025 13:04:01 +0000",
         "publishedParsed": "2025-10-04T13:04:01Z",
         "author": {
             "name": "Greg Jaffe and Kenny Holston"
         },
         "authors": [
             {
                 "name": "Greg Jaffe and Kenny Holston"
             }
         ],
         "guid": "https://www.nytimes.com/2025/10/04/us/politics/army-recruiting-trump.html",
         "categories": [
             "United States Defense and Military Forces",
             "Tests and Examinations",
             "Draft and Recruitment (Military)",
             "United States Army",
             "Hegseth, Pete",
             "Trump, Donald J",
             "Fort Jackson (SC)",
             "vis-photo",
             "audio-neutral-immersive",
             "audio-neutral-informative"
         ],
         "dcExt": {
             "creator": [
                 "Greg Jaffe and Kenny Holston"
             ]
         },
         "extensions": {
             "atom": {
                 "link": [
                     {
                         "name": "link",
                         "value": "",
                         "attrs": {
                             "href": "https://www.nytimes.com/2025/10/04/us/politics/army-recruiting-trump.html",
                             "rel": "standout"
                         },
                         "children": {}
                     }
                 ]
             },
             "dc": {
                 "creator": [
                     {
                         "name": "creator",
                         "value": "Greg Jaffe and Kenny Holston",
                         "attrs": {},
                         "children": {}
                     }
                 ]
             }
         }
     },
     {
         "title": "How Private Equity Oversees the Ethics of Drug Research",
         "description": "Many drug trials are vetted by companies with ties to the drugmakers, raising concerns about conflicts of interest and patient safety.",
         "link": "https://www.nytimes.com/2025/10/04/health/drug-trials-ethics-ozempic.html",
         "links": [
             "https://www.nytimes.com/2025/10/04/health/drug-trials-ethics-ozempic.html"
         ],
         "published": "Sat, 04 Oct 2025 09:00:13 +0000",
         "publishedParsed": "2025-10-04T09:00:13Z",
         "author": {
             "name": "Walt Bogdanich, Carson Kessler and Jeremy Singer-Vine"
         },
         "authors": [
             {
                 "name": "Walt Bogdanich, Carson Kessler and Jeremy Singer-Vine"
             }
         ],
         "guid": "https://www.nytimes.com/2025/10/04/health/drug-trials-ethics-ozempic.html",
         "image": {
             "url": "https://static01.nyt.com/images/2025/08/27/multimedia/INV-IRBs/INV-IRBs-mediumSquareAt3X.jpg"
         },
         "categories": [
             "Drugs (Pharmaceuticals)",
             "Private Equity",
             "Ethics and Official Misconduct",
             "Clinical Trials",
             "Conflicts of Interest",
             "Ozempic (Drug)",
             "Novo Nordisk A/S",
             "GLP-1 RAs (Drug)",
             "Regulation and Deregulation of Industry",
             "Mergers, Acquisitions and Divestitures",
             "Research",
             "WCG Clinical"
         ],
         "dcExt": {
             "creator": [
                 "Walt Bogdanich, Carson Kessler and Jeremy Singer-Vine"
             ]
         },
         "extensions": {
             "atom": {
                 "link": [
                     {
                         "name": "link",
                         "value": "",
                         "attrs": {
                             "href": "https://www.nytimes.com/2025/10/04/health/drug-trials-ethics-ozempic.html",
                             "rel": "standout"
                         },
                         "children": {}
                     }
                 ]
             },
             "dc": {
                 "creator": [
                     {
                         "name": "creator",
                         "value": "Walt Bogdanich, Carson Kessler and Jeremy Singer-Vine",
                         "attrs": {},
                         "children": {}
                     }
                 ]
             },
             "media": {
                 "content": [
                     {
                         "name": "content",
                         "value": "",
                         "attrs": {
                             "height": "1800",
                             "medium": "image",
                             "url": "https://static01.nyt.com/images/2025/08/27/multimedia/INV-IRBs/INV-IRBs-mediumSquareAt3X.jpg",
                             "width": "1800"
                         },
                         "children": {}
                     }
                 ],
                 "credit": [
                     {
                         "name": "credit",
                         "value": "Blake Cale",
                         "attrs": {},
                         "children": {}
                     }
                 ]
             }
         }
     },
     {
         "title": "The Tech Jester Who Pranks San Francisco",
         "description": "Riley Walz, 23, has gained fame for his online antics. His latest stunt has upset city officials.",
         "link": "https://www.nytimes.com/2025/10/04/us/riley-walz-san-francisco-parking-tickets-app.html",
         "links": [
             "https://www.nytimes.com/2025/10/04/us/riley-walz-san-francisco-parking-tickets-app.html"
         ],
         "published": "Sat, 04 Oct 2025 09:00:58 +0000",
         "publishedParsed": "2025-10-04T09:00:58Z",
         "author": {
             "name": "Heather Knight"
         },
         "authors": [
             {
                 "name": "Heather Knight"
             }
         ],
         "guid": "https://www.nytimes.com/2025/10/04/us/riley-walz-san-francisco-parking-tickets-app.html",
         "image": {
             "url": "https://static01.nyt.com/images/2025/10/01/multimedia/00nat-sf-rogue-01-mgtp/00nat-sf-rogue-01-mgtp-mediumSquareAt3X-v2.jpg"
         },
         "categories": [
             "Hoaxes and Pranks",
             "California",
             "San Francisco (Calif)",
             "San Francisco Bay Area (Calif)"
         ],
         "dcExt": {
             "creator": [
                 "Heather Knight"
             ]
         },
         "extensions": {
             "atom": {
                 "link": [
                     {
                         "name": "link",
                         "value": "",
                         "attrs": {
                             "href": "https://www.nytimes.com/2025/10/04/us/riley-walz-san-francisco-parking-tickets-app.html",
                             "rel": "standout"
                         },
                         "children": {}
                     }
                 ]
             },
             "dc": {
                 "creator": [
                     {
                         "name": "creator",
                         "value": "Heather Knight",
                         "attrs": {},
                         "children": {}
                     }
                 ]
             },
             "media": {
                 "content": [
                     {
                         "name": "content",
                         "value": "",
                         "attrs": {
                             "height": "1801",
                             "medium": "image",
                             "url": "https://static01.nyt.com/images/2025/10/01/multimedia/00nat-sf-rogue-01-mgtp/00nat-sf-rogue-01-mgtp-mediumSquareAt3X-v2.jpg",
                             "width": "1800"
                         },
                         "children": {}
                     }
                 ],
                 "credit": [
                     {
                         "name": "credit",
                         "value": "Poppy Lynch for The New York Times",
                         "attrs": {},
                         "children": {}
                     }
                 ],
                 "description": [
                     {
                         "name": "description",
                         "value": "San Francisco has long embraced eccentrics and their wacky ideas. Riley Walz is right at home.",
                         "attrs": {},
                         "children": {}
                     }
                 ]
             }
         }
     },
     {
         "title": "When A.I. Came for Hollywood",
         "description": "The Dream Factory is going full fantasy, human factor be damned.",
         "link": "https://www.nytimes.com/2025/10/04/opinion/ai-hollywood-tilly-norwood-actress.html",
         "links": [
             "https://www.nytimes.com/2025/10/04/opinion/ai-hollywood-tilly-norwood-actress.html"
         ],
         "published": "Sat, 04 Oct 2025 11:00:23 +0000",
         "publishedParsed": "2025-10-04T11:00:23Z",
         "author": {
             "name": "Maureen Dowd"
         },
         "authors": [
             {
                 "name": "Maureen Dowd"
             }
         ],
         "guid": "https://www.nytimes.com/2025/10/04/opinion/ai-hollywood-tilly-norwood-actress.html",
         "image": {
             "url": "https://static01.nyt.com/images/2025/10/05/opinion/05dowd-AI-Generated/04dowd-AI-Generated-mediumSquareAt3X.jpg"
         },
         "categories": [
             "Artificial Intelligence",
             "Movies",
             "Actors and Actresses",
             "Blunt, Emily",
             "Lanier, Jaron",
             "Hollywood (Calif)"
         ],
         "dcExt": {
             "creator": [
                 "Maureen Dowd"
             ]
         },
         "extensions": {
             "atom": {
                 "link": [
                     {
                         "name": "link",
                         "value": "",
                         "attrs": {
                             "href": "https://www.nytimes.com/2025/10/04/opinion/ai-hollywood-tilly-norwood-actress.html",
                             "rel": "standout"
                         },
                         "children": {}
                     }
                 ]
             },
             "dc": {
                 "creator": [
                     {
                         "name": "creator",
                         "value": "Maureen Dowd",
                         "attrs": {},
                         "children": {}
                     }
                 ]
             },
             "media": {
                 "content": [
                     {
                         "name": "content",
                         "value": "",
                         "attrs": {
                             "height": "1800",
                             "medium": "image",
                             "url": "https://static01.nyt.com/images/2025/10/05/opinion/05dowd-AI-Generated/04dowd-AI-Generated-mediumSquareAt3X.jpg",
                             "width": "1800"
                         },
                         "children": {}
                     }
                 ],
                 "credit": [
                     {
                         "name": "credit",
                         "value": "Illustration by The New York Times; A.I. image by Particle6 Group, via Reuters",
                         "attrs": {},
                         "children": {}
                     }
                 ]
             }
         }
     },
     {
         "title": "Best Intentions",
         "description": "Everyone’s “intentional” these days, but don’t let the word’s wholesale application to every activity of modern life deprive you of its benefits.",
         "link": "https://www.nytimes.com/2025/10/04/briefing/best-intentions.html",
         "links": [
             "https://www.nytimes.com/2025/10/04/briefing/best-intentions.html"
         ],
         "published": "Sat, 04 Oct 2025 10:21:46 +0000",
         "publishedParsed": "2025-10-04T10:21:46Z",
         "author": {
             "name": "Melissa Kirsch"
         },
         "authors": [
             {
                 "name": "Melissa Kirsch"
             }
         ],
         "guid": "https://www.nytimes.com/2025/10/04/briefing/best-intentions.html",
         "categories": [
             "internal-storyline-no",
             "Mental Health and Disorders",
             "Productivity",
             "Workplace Environment",
             "Habits and Routines (Behavior)"
         ],
         "dcExt": {
             "creator": [
                 "Melissa Kirsch"
             ]
         },
         "extensions": {
             "atom": {
                 "link": [
                     {
                         "name": "link",
                         "value": "",
                         "attrs": {
                             "href": "https://www.nytimes.com/2025/10/04/briefing/best-intentions.html",
                             "rel": "standout"
                         },
                         "children": {}
                     }
                 ]
             },
             "dc": {
                 "creator": [
                     {
                         "name": "creator",
                         "value": "Melissa Kirsch",
                         "attrs": {},
                         "children": {}
                     }
                 ]
             }
         }
     },
     {
         "title": "2 Girls Found Dead Atop a J Train in Suspected Subway Surfing Accident",
         "description": "The teenagers, found unconscious on the roof of a train in Brooklyn, appear to be the latest casualties of a popular and deadly game.",
         "link": "https://www.nytimes.com/2025/10/04/nyregion/teenage-girls-dead-subway-surfing.html",
         "links": [
             "https://www.nytimes.com/2025/10/04/nyregion/teenage-girls-dead-subway-surfing.html"
         ],
         "published": "Sat, 04 Oct 2025 16:45:52 +0000",
         "publishedParsed": "2025-10-04T16:45:52Z",
         "author": {
             "name": "Maia Coleman"
         },
         "authors": [
             {
                 "name": "Maia Coleman"
             }
         ],
         "guid": "https://www.nytimes.com/2025/10/04/nyregion/teenage-girls-dead-subway-surfing.html",
         "image": {
             "url": "https://static01.nyt.com/images/2025/10/04/multimedia/04met-subway-surf-3-ltbj/04met-subway-surf-3-ltbj-mediumSquareAt3X.jpg"
         },
         "categories": [
             "Metropolitan Transportation Authority",
             "New York City Transit Authority",
             "subway surfing",
             "Williamsburg (Brooklyn, NY)"
         ],
         "dcExt": {
             "creator": [
                 "Maia Coleman"
             ]
         },
         "extensions": {
             "atom": {
                 "link": [
                     {
                         "name": "link",
                         "value": "",
                         "attrs": {
                             "href": "https://www.nytimes.com/2025/10/04/nyregion/teenage-girls-dead-subway-surfing.html",
                             "rel": "standout"
                         },
                         "children": {}
                     }
                 ]
             },
             "dc": {
                 "creator": [
                     {
                         "name": "creator",
                         "value": "Maia Coleman",
                         "attrs": {},
                         "children": {}
                     }
                 ]
             },
             "media": {
                 "content": [
                     {
                         "name": "content",
                         "value": "",
                         "attrs": {
                             "height": "1800",
                             "medium": "image",
                             "url": "https://static01.nyt.com/images/2025/10/04/multimedia/04met-subway-surf-3-ltbj/04met-subway-surf-3-ltbj-mediumSquareAt3X.jpg",
                             "width": "1800"
                         },
                         "children": {}
                     }
                 ],
                 "credit": [
                     {
                         "name": "credit",
                         "value": "Dakota Santiago for The New York Times",
                         "attrs": {},
                         "children": {}
                     }
                 ],
                 "description": [
                     {
                         "name": "description",
                         "value": "Two girls were found dead atop a subway train in Williamsburg, Brooklyn, early Saturday.",
                         "attrs": {},
                         "children": {}
                     }
                 ]
             }
         }
     },
     {
         "title": "Sean ‘Diddy’ Combs’s Future: Prison, Fine and a Shunning",
         "description": "Many who have tracked the music mogul’s career think his reputation has been irreparably damaged by testimony of abusive behavior as a boss and boyfriend.",
         "link": "https://www.nytimes.com/2025/10/04/arts/music/sean-combs-diddy-sentenced-prison.html",
         "links": [
             "https://www.nytimes.com/2025/10/04/arts/music/sean-combs-diddy-sentenced-prison.html"
         ],
         "published": "Sat, 04 Oct 2025 10:51:52 +0000",
         "publishedParsed": "2025-10-04T10:51:52Z",
         "author": {
             "name": "Ben Sisario and Julia Jacobs"
         },
         "authors": [
             {
                 "name": "Ben Sisario and Julia Jacobs"
             }
         ],
         "guid": "https://www.nytimes.com/2025/10/04/arts/music/sean-combs-diddy-sentenced-prison.html",
         "image": {
             "url": "https://static01.nyt.com/images/2025/10/04/multimedia/04cul-combs-future-jbvt/04cul-combs-future-jbvt-mediumSquareAt3X.jpg"
         },
         "categories": [
             "Domestic Violence",
             "Sex Crimes",
             "Prostitution",
             "Pop and Rock Music",
             "Decisions and Verdicts",
             "Combs, Sean",
             "Ventura, Cassandra (Cassie)"
         ],
         "dcExt": {
             "creator": [
                 "Ben Sisario and Julia Jacobs"
             ]
         },
         "extensions": {
             "atom": {
                 "link": [
                     {
                         "name": "link",
                         "value": "",
                         "attrs": {
                             "href": "https://www.nytimes.com/2025/10/04/arts/music/sean-combs-diddy-sentenced-prison.html",
                             "rel": "standout"
                         },
                         "children": {}
                     }
                 ]
             },
             "dc": {
                 "creator": [
                     {
                         "name": "creator",
                         "value": "Ben Sisario and Julia Jacobs",
                         "attrs": {},
                         "children": {}
                     }
                 ]
             },
             "media": {
                 "content": [
                     {
                         "name": "content",
                         "value": "",
                         "attrs": {
                             "height": "1798",
                             "medium": "image",
                             "url": "https://static01.nyt.com/images/2025/10/04/multimedia/04cul-combs-future-jbvt/04cul-combs-future-jbvt-mediumSquareAt3X.jpg",
                             "width": "1800"
                         },
                         "children": {}
                     }
                 ],
                 "credit": [
                     {
                         "name": "credit",
                         "value": "Shareif Ziyadat/Getty Images",
                         "attrs": {},
                         "children": {}
                     }
                 ],
                 "description": [
                     {
                         "name": "description",
                         "value": "Imprisoned now, and damaged by graphic testimony about abusive treatment of women, Sean Combs faces a difficult climb if he ever intends to regain his status as a music producer and brand icon.",
                         "attrs": {},
                         "children": {}
                     }
                 ]
             }
         }
     },
     {
         "title": "S.C. confirms full-blown outbreak of measles",
         "content": "\u0026#32; submitted by \u0026#32; \u003ca href=\"https://www.reddit.com/user/HazyDavey68\"\u003e /u/HazyDavey68 \u003c/a\u003e \u003cbr/\u003e \u003cspan\u003e\u003ca href=\"https://www.wrdw.com/2025/10/03/safety-alert-sc-confirms-full-blown-outbreak-measles/\"\u003e[link]\u003c/a\u003e\u003c/span\u003e \u0026#32; \u003cspan\u003e\u003ca href=\"https://www.reddit.com/r/news/comments/1nxy5hl/sc_confirms_fullblown_outbreak_of_measles/\"\u003e[comments]\u003c/a\u003e\u003c/span\u003e",
         "link": "https://www.reddit.com/r/news/comments/1nxy5hl/sc_confirms_fullblown_outbreak_of_measles/",
         "links": [
             "https://www.reddit.com/r/news/comments/1nxy5hl/sc_confirms_fullblown_outbreak_of_measles/"
         ],
         "updated": "2025-10-04T16:14:31+00:00",
         "updatedParsed": "2025-10-04T16:14:31Z",
         "published": "2025-10-04T16:14:31+00:00",
         "publishedParsed": "2025-10-04T16:14:31Z",
         "author": {
             "name": "/u/HazyDavey68"
         },
         "authors": [
             {
                 "name": "/u/HazyDavey68"
             }
         ],
         "guid": "t3_1nxy5hl",
         "categories": [
             "r/news"
         ]
     },
     {
         "title": "Costco to sell Ozempic and Wegovy at a large discount for people without insurance",
         "content": "\u0026#32; submitted by \u0026#32; \u003ca href=\"https://www.reddit.com/user/Kinjal_Ghosh\"\u003e /u/Kinjal_Ghosh \u003c/a\u003e \u003cbr/\u003e \u003cspan\u003e\u003ca href=\"https://www.nbcnews.com/news/rcna235471\"\u003e[link]\u003c/a\u003e\u003c/span\u003e \u0026#32; \u003cspan\u003e\u003ca href=\"https://www.reddit.com/r/news/comments/1nxp5kq/costco_to_sell_ozempic_and_wegovy_at_a_large/\"\u003e[comments]\u003c/a\u003e\u003c/span\u003e",
         "link": "https://www.reddit.com/r/news/comments/1nxp5kq/costco_to_sell_ozempic_and_wegovy_at_a_large/",
         "links": [
             "https://www.reddit.com/r/news/comments/1nxp5kq/costco_to_sell_ozempic_and_wegovy_at_a_large/"
         ],
         "updated": "2025-10-04T09:07:57+00:00",
         "updatedParsed": "2025-10-04T09:07:57Z",
         "published": "2025-10-04T09:07:57+00:00",
         "publishedParsed": "2025-10-04T09:07:57Z",
         "author": {
             "name": "/u/Kinjal_Ghosh"
         },
         "authors": [
             {
                 "name": "/u/Kinjal_Ghosh"
             }
         ],
         "guid": "t3_1nxp5kq",
         "categories": [
             "r/news"
         ]
     },
     {
         "title": "Diddy sentenced to 50 months in prison",
         "content": "\u0026#32; submitted by \u0026#32; \u003ca href=\"https://www.reddit.com/user/tx_brandon\"\u003e /u/tx_brandon \u003c/a\u003e \u003cbr/\u003e \u003cspan\u003e\u003ca href=\"https://www.cnn.com/entertainment/live-news/sean-diddy-combs-sentencing-10-03-25\"\u003e[link]\u003c/a\u003e\u003c/span\u003e \u0026#32; \u003cspan\u003e\u003ca href=\"https://www.reddit.com/r/news/comments/1nxan2j/diddy_sentenced_to_50_months_in_prison/\"\u003e[comments]\u003c/a\u003e\u003c/span\u003e",
         "link": "https://www.reddit.com/r/news/comments/1nxan2j/diddy_sentenced_to_50_months_in_prison/",
         "links": [
             "https://www.reddit.com/r/news/comments/1nxan2j/diddy_sentenced_to_50_months_in_prison/"
         ],
         "updated": "2025-10-03T20:44:02+00:00",
         "updatedParsed": "2025-10-03T20:44:02Z",
         "published": "2025-10-03T20:44:02+00:00",
         "publishedParsed": "2025-10-03T20:44:02Z",
         "author": {
             "name": "/u/tx_brandon"
         },
         "authors": [
             {
                 "name": "/u/tx_brandon"
             }
         ],
         "guid": "t3_1nxan2j",
         "categories": [
             "r/news"
         ]
     },
     {
         "title": "Marineland asks Canadian government for emergency cash to feed whales or euthanasia imminent",
         "content": "\u0026#32; submitted by \u0026#32; \u003ca href=\"https://www.reddit.com/user/AnonRetro\"\u003e /u/AnonRetro \u003c/a\u003e \u003cbr/\u003e \u003cspan\u003e\u003ca href=\"https://apnews.com/article/whales-marineland-canada-belugas-2ede29f44bd0dc949f3879a2520b6be8\"\u003e[link]\u003c/a\u003e\u003c/span\u003e \u0026#32; \u003cspan\u003e\u003ca href=\"https://www.reddit.com/r/news/comments/1nxhncm/marineland_asks_canadian_government_for_emergency/\"\u003e[comments]\u003c/a\u003e\u003c/span\u003e",
         "link": "https://www.reddit.com/r/news/comments/1nxhncm/marineland_asks_canadian_government_for_emergency/",
         "links": [
             "https://www.reddit.com/r/news/comments/1nxhncm/marineland_asks_canadian_government_for_emergency/"
         ],
         "updated": "2025-10-04T01:57:44+00:00",
         "updatedParsed": "2025-10-04T01:57:44Z",
         "published": "2025-10-04T01:57:44+00:00",
         "publishedParsed": "2025-10-04T01:57:44Z",
         "author": {
             "name": "/u/AnonRetro"
         },
         "authors": [
             {
                 "name": "/u/AnonRetro"
             }
         ],
         "guid": "t3_1nxhncm",
         "categories": [
             "r/news"
         ]
     },
     {
         "title": "Emerging climbing star Balin Miller, 23, dies in fall from El Capitan",
         "content": "\u0026#32; submitted by \u0026#32; \u003ca href=\"https://www.reddit.com/user/MasterpieceAlone8552\"\u003e /u/MasterpieceAlone8552 \u003c/a\u003e \u003cbr/\u003e \u003cspan\u003e\u003ca href=\"https://www.theguardian.com/sport/2025/oct/02/balin-miller-climber-death-el-capitan\"\u003e[link]\u003c/a\u003e\u003c/span\u003e \u0026#32; \u003cspan\u003e\u003ca href=\"https://www.reddit.com/r/news/comments/1nwuw79/emerging_climbing_star_balin_miller_23_dies_in/\"\u003e[comments]\u003c/a\u003e\u003c/span\u003e",
         "link": "https://www.reddit.com/r/news/comments/1nwuw79/emerging_climbing_star_balin_miller_23_dies_in/",
         "links": [
             "https://www.reddit.com/r/news/comments/1nwuw79/emerging_climbing_star_balin_miller_23_dies_in/"
         ],
         "updated": "2025-10-03T09:58:49+00:00",
         "updatedParsed": "2025-10-03T09:58:49Z",
         "published": "2025-10-03T09:58:49+00:00",
         "publishedParsed": "2025-10-03T09:58:49Z",
         "author": {
             "name": "/u/MasterpieceAlone8552"
         },
         "authors": [
             {
                 "name": "/u/MasterpieceAlone8552"
             }
         ],
         "guid": "t3_1nwuw79",
         "categories": [
             "r/news"
         ]
     },
     {
         "title": "Scam Kingpins Who Ran Billion-Dollar Criminal Empire Sentenced to Death in China",
         "content": "\u0026#32; submitted by \u0026#32; \u003ca href=\"https://www.reddit.com/user/EssoEssex\"\u003e /u/EssoEssex \u003c/a\u003e \u003cbr/\u003e \u003cspan\u003e\u003ca href=\"https://www.cnn.com/2025/09/30/china/kokang-scam-center-china-myanmar-ming-family-intl-hnk\"\u003e[link]\u003c/a\u003e\u003c/span\u003e \u0026#32; \u003cspan\u003e\u003ca href=\"https://www.reddit.com/r/news/comments/1nx0oo3/scam_kingpins_who_ran_billiondollar_criminal/\"\u003e[comments]\u003c/a\u003e\u003c/span\u003e",
         "link": "https://www.reddit.com/r/news/comments/1nx0oo3/scam_kingpins_who_ran_billiondollar_criminal/",
         "links": [
             "https://www.reddit.com/r/news/comments/1nx0oo3/scam_kingpins_who_ran_billiondollar_criminal/"
         ],
         "updated": "2025-10-03T14:28:19+00:00",
         "updatedParsed": "2025-10-03T14:28:19Z",
         "published": "2025-10-03T14:28:19+00:00",
         "publishedParsed": "2025-10-03T14:28:19Z",
         "author": {
             "name": "/u/EssoEssex"
         },
         "authors": [
             {
                 "name": "/u/EssoEssex"
             }
         ],
         "guid": "t3_1nx0oo3",
         "categories": [
             "r/news"
         ]
     },
     {
         "title": "Tyrese Gibson booked on animal cruelty charge in dog case",
         "content": "\u0026#32; submitted by \u0026#32; \u003ca href=\"https://www.reddit.com/user/gmorgan99\"\u003e /u/gmorgan99 \u003c/a\u003e \u003cbr/\u003e \u003cspan\u003e\u003ca href=\"https://www.nbcnews.com/news/us-news/tyrese-gibson-dog-mauling-arrest-rcna235188\"\u003e[link]\u003c/a\u003e\u003c/span\u003e \u0026#32; \u003cspan\u003e\u003ca href=\"https://www.reddit.com/r/news/comments/1nx71oc/tyrese_gibson_booked_on_animal_cruelty_charge_in/\"\u003e[comments]\u003c/a\u003e\u003c/span\u003e",
         "link": "https://www.reddit.com/r/news/comments/1nx71oc/tyrese_gibson_booked_on_animal_cruelty_charge_in/",
         "links": [
             "https://www.reddit.com/r/news/comments/1nx71oc/tyrese_gibson_booked_on_animal_cruelty_charge_in/"
         ],
         "updated": "2025-10-03T18:25:34+00:00",
         "updatedParsed": "2025-10-03T18:25:34Z",
         "published": "2025-10-03T18:25:34+00:00",
         "publishedParsed": "2025-10-03T18:25:34Z",
         "author": {
             "name": "/u/gmorgan99"
         },
         "authors": [
             {
                 "name": "/u/gmorgan99"
             }
         ],
         "guid": "t3_1nx71oc",
         "categories": [
             "r/news"
         ]
     },
     {
         "title": "Major pharmacy chain closes all locations across U.S.",
         "content": "\u0026#32; submitted by \u0026#32; \u003ca href=\"https://www.reddit.com/user/L0v3_1s_War\"\u003e /u/L0v3_1s_War \u003c/a\u003e \u003cbr/\u003e \u003cspan\u003e\u003ca href=\"https://www.mlive.com/news/2025/10/major-pharmacy-chain-closes-all-locations-across-us.html\"\u003e[link]\u003c/a\u003e\u003c/span\u003e \u0026#32; \u003cspan\u003e\u003ca href=\"https://www.reddit.com/r/news/comments/1nx4g3u/major_pharmacy_chain_closes_all_locations_across/\"\u003e[comments]\u003c/a\u003e\u003c/span\u003e",
         "link": "https://www.reddit.com/r/news/comments/1nx4g3u/major_pharmacy_chain_closes_all_locations_across/",
         "links": [
             "https://www.reddit.com/r/news/comments/1nx4g3u/major_pharmacy_chain_closes_all_locations_across/"
         ],
         "updated": "2025-10-03T16:48:51+00:00",
         "updatedParsed": "2025-10-03T16:48:51Z",
         "published": "2025-10-03T16:48:51+00:00",
         "publishedParsed": "2025-10-03T16:48:51Z",
         "author": {
             "name": "/u/L0v3_1s_War"
         },
         "authors": [
             {
                 "name": "/u/L0v3_1s_War"
             }
         ],
         "guid": "t3_1nx4g3u",
         "categories": [
             "r/news"
         ]
     },
     {
         "title": "Body camera video shows police shoot Grand Blanc church attack suspect",
         "content": "\u0026#32; submitted by \u0026#32; \u003ca href=\"https://www.reddit.com/user/unknown_gear\"\u003e /u/unknown_gear \u003c/a\u003e \u003cbr/\u003e \u003cspan\u003e\u003ca href=\"https://www.abc12.com/video/body-camera-video-shows-police-shoot-grand-blanc-church-attack-suspect/video_23e3fd08-c2d6-5a3f-86dd-d40887c955e2.html\"\u003e[link]\u003c/a\u003e\u003c/span\u003e \u0026#32; \u003cspan\u003e\u003ca href=\"https://www.reddit.com/r/news/comments/1nx6dfx/body_camera_video_shows_police_shoot_grand_blanc/\"\u003e[comments]\u003c/a\u003e\u003c/span\u003e",
         "link": "https://www.reddit.com/r/news/comments/1nx6dfx/body_camera_video_shows_police_shoot_grand_blanc/",
         "links": [
             "https://www.reddit.com/r/news/comments/1nx6dfx/body_camera_video_shows_police_shoot_grand_blanc/"
         ],
         "updated": "2025-10-03T18:00:23+00:00",
         "updatedParsed": "2025-10-03T18:00:23Z",
         "published": "2025-10-03T18:00:23+00:00",
         "publishedParsed": "2025-10-03T18:00:23Z",
         "author": {
             "name": "/u/unknown_gear"
         },
         "authors": [
             {
                 "name": "/u/unknown_gear"
             }
         ],
         "guid": "t3_1nx6dfx",
         "categories": [
             "r/news"
         ]
     },
     {
         "title": "Treasure hunters discover $1m in silver and gold coins off Florida coast",
         "content": "\u0026#32; submitted by \u0026#32; \u003ca href=\"https://www.reddit.com/user/AudibleNod\"\u003e /u/AudibleNod \u003c/a\u003e \u003cbr/\u003e \u003cspan\u003e\u003ca href=\"https://www.theguardian.com/us-news/2025/oct/02/treasure-florida-spanish-coins\"\u003e[link]\u003c/a\u003e\u003c/span\u003e \u0026#32; \u003cspan\u003e\u003ca href=\"https://www.reddit.com/r/news/comments/1nx47lh/treasure_hunters_discover_1m_in_silver_and_gold/\"\u003e[comments]\u003c/a\u003e\u003c/span\u003e",
         "link": "https://www.reddit.com/r/news/comments/1nx47lh/treasure_hunters_discover_1m_in_silver_and_gold/",
         "links": [
             "https://www.reddit.com/r/news/comments/1nx47lh/treasure_hunters_discover_1m_in_silver_and_gold/"
         ],
         "updated": "2025-10-03T16:40:08+00:00",
         "updatedParsed": "2025-10-03T16:40:08Z",
         "published": "2025-10-03T16:40:08+00:00",
         "publishedParsed": "2025-10-03T16:40:08Z",
         "author": {
             "name": "/u/AudibleNod"
         },
         "authors": [
             {
                 "name": "/u/AudibleNod"
             }
         ],
         "guid": "t3_1nx47lh",
         "categories": [
             "r/news"
         ]
     },
     {
         "title": "Keeping Up Appearances star Patricia Routledge dies at 96",
         "content": "\u0026#32; submitted by \u0026#32; \u003ca href=\"https://www.reddit.com/user/be_sugary\"\u003e /u/be_sugary \u003c/a\u003e \u003cbr/\u003e \u003cspan\u003e\u003ca href=\"https://www.bbc.com/news/articles/czdjegvjz3do\"\u003e[link]\u003c/a\u003e\u003c/span\u003e \u0026#32; \u003cspan\u003e\u003ca href=\"https://www.reddit.com/r/news/comments/1nwvf93/keeping_up_appearances_star_patricia_routledge/\"\u003e[comments]\u003c/a\u003e\u003c/span\u003e",
         "link": "https://www.reddit.com/r/news/comments/1nwvf93/keeping_up_appearances_star_patricia_routledge/",
         "links": [
             "https://www.reddit.com/r/news/comments/1nwvf93/keeping_up_appearances_star_patricia_routledge/"
         ],
         "updated": "2025-10-03T10:30:11+00:00",
         "updatedParsed": "2025-10-03T10:30:11Z",
         "published": "2025-10-03T10:30:11+00:00",
         "publishedParsed": "2025-10-03T10:30:11Z",
         "author": {
             "name": "/u/be_sugary"
         },
         "authors": [
             {
                 "name": "/u/be_sugary"
             }
         ],
         "guid": "t3_1nwvf93",
         "categories": [
             "r/news"
         ]
     },
     {
         "title": "2 children killed, 2 others in critical condition in Texas truck stop shooting - ABC News - Breaking News, Latest News and Videos",
         "description": "\u003col\u003e\u003cli\u003e\u003ca href=\"https://news.google.com/rss/articles/CBMimwFBVV95cUxQNEFIM3lBSGJlYzhyNW4tZEU1Nl9ieFZwVTRIRDlnN0t6ZHRSMExuQ2Vpcy0zMEpVLXhUc1VSdEJlSjA3eG0yVFN1cm9qclViNWlZVkRvYWd0b1VtNTU3dWhGbjRyeVh0bk1lZS1wQVdMZjNyazFrQUdOSEFqbkU3ellQY1dtUkdjQjRVeEJ1a3RNN3NzQ3BrSUVnNNIBoAFBVV95cUxNcFNPdVZLd1hBTllCX2VhaFdUaU1kT2lDZnVRaXpyeGdmT2laMEcydXowNlVUbUp6dEVxQlRmd3V4N1Y3TG9ob0wxVkhrUmlSQ0F5OUpvTDExZm9saTMxS2dNM1RYRjRVeXZXZzRvTU9pQmwzT0V1LWpUZ0VGOXA2QUF3SXpWTjFaNmF3RWlOc3dZSzJBWi1oYmNoOWdPREdF?oc=5\" target=\"_blank\"\u003e2 children killed, 2 others in critical condition in Texas truck stop shooting\u003c/a\u003e\u0026nbsp;\u0026nbsp;\u003cfont color=\"#6f6f6f\"\u003eABC News - Breaking News, Latest News and Videos\u003c/font\u003e\u003c/li\u003e\u003cli\u003e\u003ca href=\"https://news.google.com/rss/articles/CBMitwFBVV95cUxQdDJUOTl6bDM1NHpUQmwwRndjLVR5ZWxrNTVrR3lZeDVSY3hjaGZhX2pacW9saDFpanI4SHFjU3VnR2k1Tm96ZUgwcXhKeFdFaXdzRmVKM3FERWFINlA4SE1SMUZQWktTQU56R1drQ251S0duVmM2ZDg3WnMxanAtZkdBbV8tcHIyUWpMSm8xVzFNUzNsVVd1WFRFUDlRU0Q1NmZmbG94c09IX1lSZXM4a2lpY2twUzjSAbwBQVVfeXFMTnptZ2JteGZyTFdEZlF0X2EzWUM5MDl4czVVYTFGdy1FNmxMR3pJeU93ckhmNzR6ajNrZkFJLVJlblVGTHpKMHA4TW9xMXFQcmJVcG1yQnFRaUw5RzBQRkVINGdFS1BvWVUzdVkyRngzeDNKNkhJcGg5eVJ2U3E5R29OR1NjbVFjbzFxbTdwUU5mdFMyLVJtd1NNbTF1TzI5dUpHRnNjWGVTUFNxeURFTTdNSUtPempBNUVPeVM?oc=5\" target=\"_blank\"\u003e2 kids killed, 2 others injured in shooting near Angleton, Brazoria County Sheriff's Office said\u003c/a\u003e\u0026nbsp;\u0026nbsp;\u003cfont color=\"#6f6f6f\"\u003eABC13 Houston\u003c/font\u003e\u003c/li\u003e\u003cli\u003e\u003ca href=\"https://news.google.com/rss/articles/CBMidEFVX3lxTE9mLUdiYW55TnZLRDJrTks0a1BSUkdWZl8zb0xjSXpoRjN0ODJ0TDN0dWNpcmNGbnBBSEpTWE0wVWFmTnNjZENOSkJSWkZSYWRkYjV5RDJoQXhOOXNqX2h3V3pIZDVjckZmeDVwU2VoQ01BYnla?oc=5\" target=\"_blank\"\u003e2 Children Are Dead and 2 Are in Critical Condition in Texas Shooting\u003c/a\u003e\u0026nbsp;\u0026nbsp;\u003cfont color=\"#6f6f6f\"\u003eThe New York Times\u003c/font\u003e\u003c/li\u003e\u003cli\u003e\u003ca href=\"https://news.google.com/rss/articles/CBMiowFBVV95cUxQTy1XUVExeEs2ZHNJSmlzd2ZoNjV5bkRrdGpBdE0yVlgxOFh6S284LU9ZNlJSU2laR0tUckI4WTJROU9aTFVjU2x6UUw0S3F1YXduZHV0VmpjSEVQYW0xR0NpWmJPUHFncmRfa0pzUnk4R05feWVqVEphWHVveWNjMnhZckY1UHVZZjVLZVdmUmRORVFER0drX2psNkhIalY3VDdV?oc=5\" target=\"_blank\"\u003eFour children shot, two killed in Brazoria County\u003c/a\u003e\u0026nbsp;\u0026nbsp;\u003cfont color=\"#6f6f6f\"\u003eClick2Houston\u003c/font\u003e\u003c/li\u003e\u003cli\u003e\u003ca href=\"https://news.google.com/rss/articles/CBMixAFBVV95cUxNWng3Z21rZE1OWTVvTGVRQmxIUWdvczYxMU5WclhNOVFZQi1JN1JwZmxXS2xLYVE2V3hiT3NXQzNaT0N1cE41VTNYZHpDNDEyZ1pWejVoTmJiTnNGNmNROTF6NHFuWVU1SjRHWVZUd3duTkFWMHlLTUJ3QjMtMHRPVGV0RUZySlpHVDVQb1NfVEQ0aXhxdmIwVWdiS2xscFZubkprcDJfaXpYbktneGpNa29lYnFhSkVZWTFrYTZHNTMtSjAt?oc=5\" target=\"_blank\"\u003e2 children dead, 2 critically hurt in shooting in Angleton area, sheriff's office says\u003c/a\u003e\u0026nbsp;\u0026nbsp;\u003cfont color=\"#6f6f6f\"\u003eKHOU\u003c/font\u003e\u003c/li\u003e\u003c/ol\u003e",
         "link": "https://news.google.com/rss/articles/CBMimwFBVV95cUxQNEFIM3lBSGJlYzhyNW4tZEU1Nl9ieFZwVTRIRDlnN0t6ZHRSMExuQ2Vpcy0zMEpVLXhUc1VSdEJlSjA3eG0yVFN1cm9qclViNWlZVkRvYWd0b1VtNTU3dWhGbjRyeVh0bk1lZS1wQVdMZjNyazFrQUdOSEFqbkU3ellQY1dtUkdjQjRVeEJ1a3RNN3NzQ3BrSUVnNNIBoAFBVV95cUxNcFNPdVZLd1hBTllCX2VhaFdUaU1kT2lDZnVRaXpyeGdmT2laMEcydXowNlVUbUp6dEVxQlRmd3V4N1Y3TG9ob0wxVkhrUmlSQ0F5OUpvTDExZm9saTMxS2dNM1RYRjRVeXZXZzRvTU9pQmwzT0V1LWpUZ0VGOXA2QUF3SXpWTjFaNmF3RWlOc3dZSzJBWi1oYmNoOWdPREdF?oc=5",
         "links": [
             "https://news.google.com/rss/articles/CBMimwFBVV95cUxQNEFIM3lBSGJlYzhyNW4tZEU1Nl9ieFZwVTRIRDlnN0t6ZHRSMExuQ2Vpcy0zMEpVLXhUc1VSdEJlSjA3eG0yVFN1cm9qclViNWlZVkRvYWd0b1VtNTU3dWhGbjRyeVh0bk1lZS1wQVdMZjNyazFrQUdOSEFqbkU3ellQY1dtUkdjQjRVeEJ1a3RNN3NzQ3BrSUVnNNIBoAFBVV95cUxNcFNPdVZLd1hBTllCX2VhaFdUaU1kT2lDZnVRaXpyeGdmT2laMEcydXowNlVUbUp6dEVxQlRmd3V4N1Y3TG9ob0wxVkhrUmlSQ0F5OUpvTDExZm9saTMxS2dNM1RYRjRVeXZXZzRvTU9pQmwzT0V1LWpUZ0VGOXA2QUF3SXpWTjFaNmF3RWlOc3dZSzJBWi1oYmNoOWdPREdF?oc=5"
         ],
         "published": "Sat, 04 Oct 2025 17:46:55 GMT",
         "publishedParsed": "2025-10-04T17:46:55Z",
         "guid": "CBMimwFBVV95cUxQNEFIM3lBSGJlYzhyNW4tZEU1Nl9ieFZwVTRIRDlnN0t6ZHRSMExuQ2Vpcy0zMEpVLXhUc1VSdEJlSjA3eG0yVFN1cm9qclViNWlZVkRvYWd0b1VtNTU3dWhGbjRyeVh0bk1lZS1wQVdMZjNyazFrQUdOSEFqbkU3ellQY1dtUkdjQjRVeEJ1a3RNN3NzQ3BrSUVnNNIBoAFBVV95cUxNcFNPdVZLd1hBTllCX2VhaFdUaU1kT2lDZnVRaXpyeGdmT2laMEcydXowNlVUbUp6dEVxQlRmd3V4N1Y3TG9ob0wxVkhrUmlSQ0F5OUpvTDExZm9saTMxS2dNM1RYRjRVeXZXZzRvTU9pQmwzT0V1LWpUZ0VGOXA2QUF3SXpWTjFaNmF3RWlOc3dZSzJBWi1oYmNoOWdPREdF"
     },
     {
         "title": "'Drop it now!': Video shows Michigan church shooter was ordered to give up before he was killed - AP News",
         "description": "\u003col\u003e\u003cli\u003e\u003ca href=\"https://news.google.com/rss/articles/CBMipAFBVV95cUxPZ3IwZGZBQnFYTGw1R1oxbWNTWUx1QVRkUVZrQUJpTUJ2WGEybTMwR09XVlZMd2FJRlpDNmUyLXN2SnpuSDVFX1B5Qm54Vm5tbFhFUjJDOEdqSHR5WlhWcDU4a3J0TGE0YVFMQTZIVmFiZVB5MmxpLTI5VGJOaF93Vy1PTkNNNEk3MUJDVGtFZEZJcmdvV1E1WlEwbVY4ZWRMUDBHUQ?oc=5\" target=\"_blank\"\u003e'Drop it now!': Video shows Michigan church shooter was ordered to give up before he was killed\u003c/a\u003e\u0026nbsp;\u0026nbsp;\u003cfont color=\"#6f6f6f\"\u003eAP News\u003c/font\u003e\u003c/li\u003e\u003cli\u003e\u003ca href=\"https://news.google.com/rss/articles/CBMi1AFBVV95cUxNdUszV2Nxajd2bDIxaEhaTTA5NkgyN0JtY1BfU0ZqM3RSbVloT19KQmd5MmRSblBhbDg5a0pKSmRDRFFIcV9sN1BWeFNZOFBYSWQ4RkZEbmhOdXBhc2JTcXU0WUYyZHY5aVJCRVdiMFlPVzM4Q3B2VC1jWTItNEotQm02SVBnWVQ0RUpPVnIzV014dFVNejI4WWUwU0R5cHRSOGVUZ2lWN0VkTDN1YUhiZk5jSzNTR05vS1RidWFZUmE4X0xRS1JZcUFEZ0VoWGZDNXphUQ?oc=5\" target=\"_blank\"\u003eMeet the teenager credited with saving family’s life during Michigan church attack\u003c/a\u003e\u0026nbsp;\u0026nbsp;\u003cfont color=\"#6f6f6f\"\u003eClickOnDetroit\u003c/font\u003e\u003c/li\u003e\u003cli\u003e\u003ca href=\"https://news.google.com/rss/articles/CBMiywFBVV95cUxPcDFLNk5IUVZjaGFFMDl0LXE1T1REUFVUQkRpOVoycEdacndpYjBsRDZ3akVzQ3J2ZEpwMDliSzFuSDdFT2ZZS3R5Nk1Ib3JDR01kOHUtZjZYV25mQWNKemxpLTVkR1c5aGp2WUhHUEVBbURvajJRVnl0d184UGZ4VHk2N24tckhWa2x1ZnBKLU5ONGhfWDhRVTEwbVBfUVc0QzE1cDZFRFl4TWF1MHV0eGg2OFEyLW5SaktfWmdpUmdiY05rTWxmVlI5VQ?oc=5\" target=\"_blank\"\u003eGrand Blanc Twp. church attack draws hundreds of faith leaders for safety training\u003c/a\u003e\u0026nbsp;\u0026nbsp;\u003cfont color=\"#6f6f6f\"\u003eDetroit Free Press\u003c/font\u003e\u003c/li\u003e\u003cli\u003e\u003ca href=\"https://news.google.com/rss/articles/CBMimgFBVV95cUxQR0diZzVjY2puY1lFOVpJN0NycWRvT0RqckdOSHZjOEZsa09LaDN6bWJhRGdOSzJmM1lNVzZ5bjBsMHdNTUpLd3N5VklDZzREU2lNOHZkWFlNaENVck56ck1ZemlDMGpJejNkNXk5SW1KaDFTZ3JHX0pvWHpfdzI5WndGMWFDS2VkTUMxc3VxYlJVdm5GdUE0R1Vn0gGfAUFVX3lxTE1Ib19QejdWVW9QV0E3andxQXpkc3hmZDI1MXVkWEFQZjMxY3VEMU5lSFpZWFlEZzE2cmZhOXo2Z040YkVqZElkUmdPZEVIM1ZYRm9SbU9ZQjlrblJmcEJGYjUyTWg1OVFNNW4xRVBzTXB3d0tDOTVLbFpOdW1fVFJKWGpUNkZsekZxaVVWVTRsb1VzeTA1QVU5T0VjV3BFVQ?oc=5\" target=\"_blank\"\u003eMichigan church shooting bodycam video shows police confront gunman\u003c/a\u003e\u0026nbsp;\u0026nbsp;\u003cfont color=\"#6f6f6f\"\u003eFox News\u003c/font\u003e\u003c/li\u003e\u003cli\u003e\u003ca href=\"https://news.google.com/rss/articles/CBMiqgFBVV95cUxNQlltaDhvTUg0OVpsR0dHd1RVQjQzeUhmZTZqMTV6d3E5Z0xIaGQ4aGppMHVWUDZRaTkybkpBREx1SWVuVWt1LW5jNy1OdE9rSjR4LUZfZnB5cEk5MVVqa29vQ2hOOVhKdUN6WUs1bm83UUpISzJGTi0zSVRGZ2lHSUtiNVAyc3paTUIzbnAwT1lhQ19INE1BLURSbWZkNVlLRDkzQWZwY2RDQQ?oc=5\" target=\"_blank\"\u003eLatter-day Saints churchgoers raise money for family of accused mass shooter\u003c/a\u003e\u0026nbsp;\u0026nbsp;\u003cfont color=\"#6f6f6f\"\u003eCBS News\u003c/font\u003e\u003c/li\u003e\u003c/ol\u003e",
         "link": "https://news.google.com/rss/articles/CBMipAFBVV95cUxPZ3IwZGZBQnFYTGw1R1oxbWNTWUx1QVRkUVZrQUJpTUJ2WGEybTMwR09XVlZMd2FJRlpDNmUyLXN2SnpuSDVFX1B5Qm54Vm5tbFhFUjJDOEdqSHR5WlhWcDU4a3J0TGE0YVFMQTZIVmFiZVB5MmxpLTI5VGJOaF93Vy1PTkNNNEk3MUJDVGtFZEZJcmdvV1E1WlEwbVY4ZWRMUDBHUQ?oc=5",
         "links": [
             "https://news.google.com/rss/articles/CBMipAFBVV95cUxPZ3IwZGZBQnFYTGw1R1oxbWNTWUx1QVRkUVZrQUJpTUJ2WGEybTMwR09XVlZMd2FJRlpDNmUyLXN2SnpuSDVFX1B5Qm54Vm5tbFhFUjJDOEdqSHR5WlhWcDU4a3J0TGE0YVFMQTZIVmFiZVB5MmxpLTI5VGJOaF93Vy1PTkNNNEk3MUJDVGtFZEZJcmdvV1E1WlEwbVY4ZWRMUDBHUQ?oc=5"
         ],
         "published": "Fri, 03 Oct 2025 21:49:00 GMT",
         "publishedParsed": "2025-10-03T21:49:00Z",
         "guid": "CBMipAFBVV95cUxPZ3IwZGZBQnFYTGw1R1oxbWNTWUx1QVRkUVZrQUJpTUJ2WGEybTMwR09XVlZMd2FJRlpDNmUyLXN2SnpuSDVFX1B5Qm54Vm5tbFhFUjJDOEdqSHR5WlhWcDU4a3J0TGE0YVFMQTZIVmFiZVB5MmxpLTI5VGJOaF93Vy1PTkNNNEk3MUJDVGtFZEZJcmdvV1E1WlEwbVY4ZWRMUDBHUQ"
     },
     {
         "title": "Chevron fire expected to spark jump in prices at the gas pump - Los Angeles Times",
         "description": "\u003col\u003e\u003cli\u003e\u003ca href=\"https://news.google.com/rss/articles/CBMihAFBVV95cUxOdnBkT2dSQmNkbFZFTzl0cnh2NkxDTG5mbFRISUUwdjYwNGcxYm03U1QzT1BBUjNMVkRLNXBCcU1KblR2bzdwdUdabEJwY0JfNEtrNk1oc2NfS3lhM2FoanIyNEtKYWdaZ0R5a0tqSFljTHBiVHNFZmJzeU1QNjlveWphZm4?oc=5\" target=\"_blank\"\u003eChevron fire expected to spark jump in prices at the gas pump\u003c/a\u003e\u0026nbsp;\u0026nbsp;\u003cfont color=\"#6f6f6f\"\u003eLos Angeles Times\u003c/font\u003e\u003c/li\u003e\u003cli\u003e\u003ca href=\"https://news.google.com/rss/articles/CBMixgFBVV95cUxOeWpNOEJGcThic0JEMUZMSUtadUZnaEpDS2RueTNPVE9NV0RKTjk4UDk2UFVPRWlvc21RUHlRRHFfZ2IwUmdPM25tMGxFakhPSy1KTm8zSzJIa3Q0NjlxbGNhdkpIb3A1UjhuRm5janJmdy1MS1hMVmphT3JmOElCZ1JBQ1NLSWZOcVVzUkdacFFVZGpmV0k0VkIyV3FQOWRDZThheXVpN01DLWc0WUJWTDFPODlRRWNZOUljbWJ6enR3bkdzLVE?oc=5\" target=\"_blank\"\u003eEl Segundo was born by oil. The massive refinery fire leaves residents rattled\u003c/a\u003e\u0026nbsp;\u0026nbsp;\u003cfont color=\"#6f6f6f\"\u003eLos Angeles Times\u003c/font\u003e\u003c/li\u003e\u003cli\u003e\u003ca href=\"https://news.google.com/rss/articles/CBMiogFBVV95cUxNV2hxdzF1Q1JPcUJiZHZWaEVma0pRTGFzVlNiakhXdTJVNkVkWW5wV3dRckpOWmVhMXhBMmVWMF96ZC11Tm5xRENkWmR1ZFAzdkhEVEEzTkdmeWlFWkFfQ0JrTjJxaVdpTDAwZUIzX2xJcEw4d0UyOVpOa2hQeXByYVdpcWo2aVNBclJYRTlQT2Y3RHJPOTBPdmtzaV9maFJ2S3c?oc=5\" target=\"_blank\"\u003eHere's how much gas prices could go up after massive Calif. refinery fire\u003c/a\u003e\u0026nbsp;\u0026nbsp;\u003cfont color=\"#6f6f6f\"\u003eSFGATE\u003c/font\u003e\u003c/li\u003e\u003cli\u003e\u003ca href=\"https://news.google.com/rss/articles/CBMiuwFBVV95cUxOYXJxNFE2R1E1ZU9qUGJaMDZkWVRVZ1ZGUXdFdFUyUHMtLUxaUWM0U3VUaXd6cFlPeGFoR3VHaXFOZzBXZWxqZjA2ZmZQazFtU3Y0djltbC1XZ3ZYNHFhRkdzQ09HekJfcHFTbllEX2RycVUwdzBqR3ZaRVB6cWliVFJ0ZUNQdDVrSlpWZ3V6cHJHcnZTUlhxcndveDYzS3J1Y204STJOYjdoSGlGVEVnM2NRSU9adWtyVW5R0gHAAUFVX3lxTE1sOHFpMHNNRjFHMDNkRzJLQ1VnYWladHJ0bVNTWURrYnNnUHZiTDE5bkZNSXVJYUR2N3VFaUQtbkJaS0NobFE2ZFBjTVpIeU5lTXVBUDVvWkU1YlZIQk9SNTRYZGhkT0ZZVi1VY1lQbExfOW1pNEo2MXB6bk9SYVN0bTltd0MyNmY1Qnp5SkFObFNlOFdxVjg1S1FDTEZEQVljeXplLWFYbDAzcThYb3RpbEFld0lKeWxoa2FjTDRPNw?oc=5\" target=\"_blank\"\u003eEl Segundo Chevron refinery explosion, fire sparks health concerns for some: What to know about air quality\u003c/a\u003e\u0026nbsp;\u0026nbsp;\u003cfont color=\"#6f6f6f\"\u003eABC7 Los Angeles\u003c/font\u003e\u003c/li\u003e\u003cli\u003e\u003ca href=\"https://news.google.com/rss/articles/CBMiWkFVX3lxTFBjbzJaSjZOUndpdDJLU1NwdmVFci1FQndOYUpMQ3l1anJDZU5NV0xram9IZFczNWNQTnBKLTlSa1FPdjJqcTlhM3NGUG9BVVBtLTBYbFVpZzliQQ?oc=5\" target=\"_blank\"\u003eMassive fire at Chevron refinery in California contained, officials say\u003c/a\u003e\u0026nbsp;\u0026nbsp;\u003cfont color=\"#6f6f6f\"\u003eBBC\u003c/font\u003e\u003c/li\u003e\u003c/ol\u003e",
         "link": "https://news.google.com/rss/articles/CBMihAFBVV95cUxOdnBkT2dSQmNkbFZFTzl0cnh2NkxDTG5mbFRISUUwdjYwNGcxYm03U1QzT1BBUjNMVkRLNXBCcU1KblR2bzdwdUdabEJwY0JfNEtrNk1oc2NfS3lhM2FoanIyNEtKYWdaZ0R5a0tqSFljTHBiVHNFZmJzeU1QNjlveWphZm4?oc=5",
         "links": [
             "https://news.google.com/rss/articles/CBMihAFBVV95cUxOdnBkT2dSQmNkbFZFTzl0cnh2NkxDTG5mbFRISUUwdjYwNGcxYm03U1QzT1BBUjNMVkRLNXBCcU1KblR2bzdwdUdabEJwY0JfNEtrNk1oc2NfS3lhM2FoanIyNEtKYWdaZ0R5a0tqSFljTHBiVHNFZmJzeU1QNjlveWphZm4?oc=5"
         ],
         "published": "Fri, 03 Oct 2025 18:22:12 GMT",
         "publishedParsed": "2025-10-03T18:22:12Z",
         "guid": "CBMihAFBVV95cUxOdnBkT2dSQmNkbFZFTzl0cnh2NkxDTG5mbFRISUUwdjYwNGcxYm03U1QzT1BBUjNMVkRLNXBCcU1KblR2bzdwdUdabEJwY0JfNEtrNk1oc2NfS3lhM2FoanIyNEtKYWdaZ0R5a0tqSFljTHBiVHNFZmJzeU1QNjlveWphZm4"
     },
     {
         "title": "2 Teen Girls Died In a Hit-And-Run. Another Teen Faces Murder Charges. - The New York Times",
         "description": "\u003col\u003e\u003cli\u003e\u003ca href=\"https://news.google.com/rss/articles/CBMijAFBVV95cUxNOUtwbTM1QzdsY2JKR3lwZ2NOeWFKVXozQmxkemRZNTNLQ1hXcUV2ODE4UE9PS281d2JDUFNkMFZpaEhqMjFjZDhRbVpaSXBnODRVdTVKbGZ6WGd3Sm5McV9lZ1lDanBDbFdMQVl2cldncGpYQjdHZ05MVF9YVVVXSXJUbkUxSkNjX3JLUA?oc=5\" target=\"_blank\"\u003e2 Teen Girls Died In a Hit-And-Run. Another Teen Faces Murder Charges.\u003c/a\u003e\u0026nbsp;\u0026nbsp;\u003cfont color=\"#6f6f6f\"\u003eThe New York Times\u003c/font\u003e\u003c/li\u003e\u003cli\u003e\u003ca href=\"https://news.google.com/rss/articles/CBMickFVX3lxTE95RlBlalUyUTliN19XWlJFdzNHZFAxT0NuN0lxVW1SY0pJQnItN1E4V0RCR2ZVaG5IeXpEcXpJMEZPV3lud2E5cC1tVjJvUXdDdG0wb05BSEZqbVRwc18tajNhNjVyUzJjd3ZfZFAzdkdHUQ?oc=5\" target=\"_blank\"\u003eTwo teen girls went for a bike ride – and were killed by a car. Now another teen faces murder charges\u003c/a\u003e\u0026nbsp;\u0026nbsp;\u003cfont color=\"#6f6f6f\"\u003eCNN\u003c/font\u003e\u003c/li\u003e\u003cli\u003e\u003ca href=\"https://news.google.com/rss/articles/CBMiaEFVX3lxTE9lamh5bVVNMHZuQ0FFM2xYQzZkb1d3UE0xNjRwSjRTZmlwNl9hMFVwUklYNlEtWGZ5WjdpNy04Tk9sZGE2UHllcjU5c3NscmwxZ3Jua09GWm9pMUZvS08yUXJMVm9WZ0NK0gFuQVVfeXFMTTBtVzVrMEVfMFNmbGFUcVJ0LWloeUpuQTBTYWlXUGVDd2d0SS1EVzZ0Y0pEdTJ0SDZBY1lmVU5QT2tXR0t0a2tMV24yLW0zSDdINnVXY2hQSEdNWGsxZWlYMzFONFJaRHROaXhCZmc?oc=5\" target=\"_blank\"\u003eFamilies of slain Cranford teens call deadly crash ‘murder'\u003c/a\u003e\u0026nbsp;\u0026nbsp;\u003cfont color=\"#6f6f6f\"\u003eFOX 5 New York\u003c/font\u003e\u003c/li\u003e\u003cli\u003e\u003ca href=\"https://news.google.com/rss/articles/CBMilgFBVV95cUxPMUFJc0ZRclM0UnVTX0xtdXJpVC01ZkpIcjZ3S1ZuWF9lWVlXbmN0OTBNeGNQQ21iN2QtNkJyVEpXTkFXZjF3TFhUOTlpa28tMHNWaExLM3cwdmJBbGZ4Q3N2WE5rWGI0Z0l2Z1JaSXZDYmxPWUhZbUFsZVBSU0xBcnZ1dHY4TG9Bb204c2VvM1NIR1NVclHSAZ4BQVVfeXFMTzA1V0xTUmFXZ2xhbkJsWExyZWxaaUt2Q2pvcXB5YTVkWUU5Y1l0Zkp0cnlEN3JqRHZ1U0hCU2lRUEpiQW1ZTTlFTlNPbDZrN3h3TmpGZmpKN21MTTUxQVA3U3NCRWtCMUhjNS14QVZkUVg4ZjJXc25uZ0JJRTFDUUdlMEZDODdlMklFU2pMbjBKY2VGZk9rSW8tQmJxMUE?oc=5\" target=\"_blank\"\u003eDriver who allegedly mowed down 2 teens in NJ town identified, as families mourn victims\u003c/a\u003e\u0026nbsp;\u0026nbsp;\u003cfont color=\"#6f6f6f\"\u003eNBC 4 New York\u003c/font\u003e\u003c/li\u003e\u003cli\u003e\u003ca href=\"https://news.google.com/rss/articles/CBMivgFBVV95cUxQX3hTU2VWbHhMa244Wmo3d21KUGxrSnJucFFFdkxXQ3cxVWdpVk5LYTM1NEF1RGhIZVVOZG95T2hwWVdzVmh4QWRVUTAtNXkzVXJBd0l6eHVUdGozLUdWVTNKYndPTEtzT0tQbXRtdFJrX0tGZ04wd1FuT25RV0JJREE5VS1sT1Qwd1JidUt2QmN5REtic0YzUDdxOGtWaDZsWE9fYmdOMl8taG5Cb2g4b2lxRTNhaG5CUjB6NWxR0gHDAUFVX3lxTE9LYkl6SGs4dnBYNDJuQ1hhWFBCTHlFQnRYa2pOcGI3SlhQWm9zM2lVWVRsMWVUTG1INGJYTjUweGZkY2JRSFA0THdrQUNLdlVLRnl2amVJTjRLY2JtTUFodVVjb1VKTHdDUlY5bGN0TTVMdmMtZ1BBYnpQSndTQ3FsUXFHTlJaZV9uTmRUUnBWTXNPamF4YXV4VGM0OC1LUzloWVBqTTBRaXJlNHViRC00NGdKQUVhS1NUSVVrNE9iTjRXQQ?oc=5\" target=\"_blank\"\u003eFamilies claim teen murder suspect was 'plotting' deadly hit-and-run for months before killing two girls\u003c/a\u003e\u0026nbsp;\u0026nbsp;\u003cfont color=\"#6f6f6f\"\u003eFox News\u003c/font\u003e\u003c/li\u003e\u003c/ol\u003e",
         "link": "https://news.google.com/rss/articles/CBMijAFBVV95cUxNOUtwbTM1QzdsY2JKR3lwZ2NOeWFKVXozQmxkemRZNTNLQ1hXcUV2ODE4UE9PS281d2JDUFNkMFZpaEhqMjFjZDhRbVpaSXBnODRVdTVKbGZ6WGd3Sm5McV9lZ1lDanBDbFdMQVl2cldncGpYQjdHZ05MVF9YVVVXSXJUbkUxSkNjX3JLUA?oc=5",
         "links": [
             "https://news.google.com/rss/articles/CBMijAFBVV95cUxNOUtwbTM1QzdsY2JKR3lwZ2NOeWFKVXozQmxkemRZNTNLQ1hXcUV2ODE4UE9PS281d2JDUFNkMFZpaEhqMjFjZDhRbVpaSXBnODRVdTVKbGZ6WGd3Sm5McV9lZ1lDanBDbFdMQVl2cldncGpYQjdHZ05MVF9YVVVXSXJUbkUxSkNjX3JLUA?oc=5"
         ],
         "published": "Sat, 04 Oct 2025 00:32:56 GMT",
         "publishedParsed": "2025-10-04T00:32:56Z",
         "guid": "CBMijAFBVV95cUxNOUtwbTM1QzdsY2JKR3lwZ2NOeWFKVXozQmxkemRZNTNLQ1hXcUV2ODE4UE9PS281d2JDUFNkMFZpaEhqMjFjZDhRbVpaSXBnODRVdTVKbGZ6WGd3Sm5McV9lZ1lDanBDbFdMQVl2cldncGpYQjdHZ05MVF9YVVVXSXJUbkUxSkNjX3JLUA"
     },
     {
         "title": "How often has general conference happened without the First Presidency in place? - KSL TV 5",
         "description": "\u003col\u003e\u003cli\u003e\u003ca href=\"https://news.google.com/rss/articles/CBMifEFVX3lxTE5qd3JyMHRYcVRiVll0cU43TVg3WlVjQnNMU0wxZlFvU3BabHk2RXBxXzlLaVdvYklINTJQaThxLXo5Mngwd19RNzQ3dHJKMlF5NXlGRE55cFpoZFRia05XdWdOVERZYkJ0cnRlaXBOM2taS2JrOV9TNXM3X0w?oc=5\" target=\"_blank\"\u003eHow often has general conference happened without the First Presidency in place?\u003c/a\u003e\u0026nbsp;\u0026nbsp;\u003cfont color=\"#6f6f6f\"\u003eKSL TV 5\u003c/font\u003e\u003c/li\u003e\u003cli\u003e\u003ca href=\"https://news.google.com/rss/articles/CBMiqwFBVV95cUxOMUZGaGJabW83anlwb3ZZNFA3U1lOMndwcGRXYnJqY2RGSkJOLVZaOUlMSjd3RWZKOUVIZmhKYWJXYm5jRVllR09Nemdpa3EwNll6N2RadG91TG5iV1cySTl1Ml8zS2FRbTg4X1NKVXpDYmhzQVNHTUFzckY5LTlsNWhHMFVWSGZSNmxCSkNYM0lycmRXVTgyT1UtT1NTdFF3RzN1eVhjd2FPT2c?oc=5\" target=\"_blank\"\u003eTalk Summaries From the October 2025 Saturday Morning Session\u003c/a\u003e\u0026nbsp;\u0026nbsp;\u003cfont color=\"#6f6f6f\"\u003enewsroom.churchofjesuschrist.org\u003c/font\u003e\u003c/li\u003e\u003cli\u003e\u003ca href=\"https://news.google.com/rss/articles/CBMirAFBVV95cUxPVl82ZVhqX0hiUFBjRnYzYUpKZDhMSzNCdWU4X1RCOVZlWWVxSkkzRncydFVHcXJPSjhSMVNxOE1reFlnR3JLMDN1X0VZSDdOSWNEaXlIUGY3ZzIxMUhDS3c5RjBmbHU4OTlFMnVKMzIwaGxST0s1ZXRXenI1aWhOODNjUG9NaUdhZjZHdnFvX3NEMWdMMGVJeGd2Q29maXFTNmZjLTllRF9jaURU?oc=5\" target=\"_blank\"\u003eOctober 2025 general conference: Announcements, talk summaries, photos, session highlights\u003c/a\u003e\u0026nbsp;\u0026nbsp;\u003cfont color=\"#6f6f6f\"\u003eChurch News\u003c/font\u003e\u003c/li\u003e\u003cli\u003e\u003ca href=\"https://news.google.com/rss/articles/CBMiuwFBVV95cUxNRlQ3THRaXzdrZjdzejlKSjVmX0U3Ny03bThlNDN6dlo3WVBEVFQ1X1FCdjdvU0hTY2lvNFd0U1FWcTZGQkhiNjNQbjhfNHhEeThLVE41WUlaQTdYWFA0NW4yT1BTTVVrSzVDcno4cVBsdFc0UnNFWUNUal9FaEtJRjhja3ZQa3F3Um5fVTJNRU1rYnJoaWVJWEhzbi16OUJ5M3pZR0ZTMjRnbk9aOTZHZUk3amhXOV9ZZ1pV?oc=5\" target=\"_blank\"\u003eHow general conference will be different and the same this weekend\u003c/a\u003e\u0026nbsp;\u0026nbsp;\u003cfont color=\"#6f6f6f\"\u003eDeseret News\u003c/font\u003e\u003c/li\u003e\u003cli\u003e\u003ca href=\"https://news.google.com/rss/articles/CBMisgFBVV95cUxQbVE2elZHa2RUZ3VKMGxOcHg3LVVJelEzVEVqa3hZVWxuTGhhbHJnYzltMW9aSDUwWTZNckpUUnFXX0RuTGlfYXR3SzZiRzVVSnJXcERGbEQxMXBwQ05QTlBWelAtUzdjT2gxVmd3cjloODFuaE50QVkxcHdUeUkweVlOZ3p2U3UtVEFrSmlkM2NoTWJRTHgzTW5UZWIxQ19VSUdDbXBKREo3SkNCbnQ3cFZ3?oc=5\" target=\"_blank\"\u003eSaturday morning session: Summaries from Latter-day Saint general conference\u003c/a\u003e\u0026nbsp;\u0026nbsp;\u003cfont color=\"#6f6f6f\"\u003eKSL.com\u003c/font\u003e\u003c/li\u003e\u003c/ol\u003e",
         "link": "https://news.google.com/rss/articles/CBMifEFVX3lxTE5qd3JyMHRYcVRiVll0cU43TVg3WlVjQnNMU0wxZlFvU3BabHk2RXBxXzlLaVdvYklINTJQaThxLXo5Mngwd19RNzQ3dHJKMlF5NXlGRE55cFpoZFRia05XdWdOVERZYkJ0cnRlaXBOM2taS2JrOV9TNXM3X0w?oc=5",
         "links": [
             "https://news.google.com/rss/articles/CBMifEFVX3lxTE5qd3JyMHRYcVRiVll0cU43TVg3WlVjQnNMU0wxZlFvU3BabHk2RXBxXzlLaVdvYklINTJQaThxLXo5Mngwd19RNzQ3dHJKMlF5NXlGRE55cFpoZFRia05XdWdOVERZYkJ0cnRlaXBOM2taS2JrOV9TNXM3X0w?oc=5"
         ],
         "published": "Fri, 03 Oct 2025 22:53:53 GMT",
         "publishedParsed": "2025-10-03T22:53:53Z",
         "guid": "CBMifEFVX3lxTE5qd3JyMHRYcVRiVll0cU43TVg3WlVjQnNMU0wxZlFvU3BabHk2RXBxXzlLaVdvYklINTJQaThxLXo5Mngwd19RNzQ3dHJKMlF5NXlGRE55cFpoZFRia05XdWdOVERZYkJ0cnRlaXBOM2taS2JrOV9TNXM3X0w"
     },
     {
         "title": "A Comparison of Ada and Rust, Using Solutions to the Advent of Code",
         "description": "\u003ca href=\"https://news.ycombinator.com/item?id=45473861\"\u003eComments\u003c/a\u003e",
         "link": "https://github.com/johnperry-math/AoC2023/blob/master/More_Detailed_Comparison.md",
         "links": [
             "https://github.com/johnperry-math/AoC2023/blob/master/More_Detailed_Comparison.md"
         ],
         "published": "Sat, 04 Oct 2025 15:10:49 +0000",
         "publishedParsed": "2025-10-04T15:10:49Z"
     },
     {
         "title": "Use theorem provers to ensure the correctness of your LLM's reasoning",
         "description": "\u003ca href=\"https://news.ycombinator.com/item?id=45475529\"\u003eComments\u003c/a\u003e",
         "link": "https://github.com/DebarghaG/proofofthought",
         "links": [
             "https://github.com/DebarghaG/proofofthought"
         ],
         "published": "Sat, 04 Oct 2025 18:34:23 +0000",
         "publishedParsed": "2025-10-04T18:34:23Z"
     },
     {
         "title": "Five Years as a Startup CTO: How, Why, and Was It Worth It?",
         "description": "\u003ca href=\"https://news.ycombinator.com/item?id=45437044\"\u003eComments\u003c/a\u003e",
         "link": "https://distinctplace.com/2024/09/11/five-years-as-startup-cto-was-it-all-worth-it/",
         "links": [
             "https://distinctplace.com/2024/09/11/five-years-as-startup-cto-was-it-all-worth-it/"
         ],
         "published": "Wed, 01 Oct 2025 12:45:52 +0000",
         "publishedParsed": "2025-10-01T12:45:52Z"
     },
     {
         "title": "Knowledge Infusion Scaling Law for Pre-Training Large Language Models",
         "description": "\u003ca href=\"https://news.ycombinator.com/item?id=45474900\"\u003eComments\u003c/a\u003e",
         "link": "https://arxiv.org/abs/2509.19371",
         "links": [
             "https://arxiv.org/abs/2509.19371"
         ],
         "published": "Sat, 04 Oct 2025 17:18:07 +0000",
         "publishedParsed": "2025-10-04T17:18:07Z"
     },
     {
         "title": "Self-Hosting Email Like It's 1984",
         "description": "\u003ca href=\"https://news.ycombinator.com/item?id=45473730\"\u003eComments\u003c/a\u003e",
         "link": "https://maxadamski.com/blog/2025/10/email.html",
         "links": [
             "https://maxadamski.com/blog/2025/10/email.html"
         ],
         "published": "Sat, 04 Oct 2025 14:53:32 +0000",
         "publishedParsed": "2025-10-04T14:53:32Z"
     },
     {
         "title": "The Buchstabenmuseum Berlin is closing",
         "description": "\u003ca href=\"https://news.ycombinator.com/item?id=45472678\"\u003eComments\u003c/a\u003e",
         "link": "https://www.buchstabenmuseum.de/en/",
         "links": [
             "https://www.buchstabenmuseum.de/en/"
         ],
         "published": "Sat, 04 Oct 2025 11:58:58 +0000",
         "publishedParsed": "2025-10-04T11:58:58Z"
     },
     {
         "title": "Thunderscan: A clever device transforms a printer into a scanner (2004)",
         "description": "\u003ca href=\"https://news.ycombinator.com/item?id=45472765\"\u003eComments\u003c/a\u003e",
         "link": "https://www.folklore.org/Thunderscan.html",
         "links": [
             "https://www.folklore.org/Thunderscan.html"
         ],
         "published": "Sat, 04 Oct 2025 12:16:37 +0000",
         "publishedParsed": "2025-10-04T12:16:37Z"
     },
     {
         "title": "Flock's gunshot detection microphones will start listening for human voices",
         "description": "\u003ca href=\"https://news.ycombinator.com/item?id=45473698\"\u003eComments\u003c/a\u003e",
         "link": "https://www.eff.org/deeplinks/2025/10/flocks-gunshot-detection-microphones-will-start-listening-human-voices",
         "links": [
             "https://www.eff.org/deeplinks/2025/10/flocks-gunshot-detection-microphones-will-start-listening-human-voices"
         ],
         "published": "Sat, 04 Oct 2025 14:49:30 +0000",
         "publishedParsed": "2025-10-04T14:49:30Z"
     },
     {
         "title": "Paged Out Issue #7 [pdf]",
         "description": "\u003ca href=\"https://news.ycombinator.com/item?id=45472319\"\u003eComments\u003c/a\u003e",
         "link": "https://pagedout.institute/download/PagedOut_007.pdf",
         "links": [
             "https://pagedout.institute/download/PagedOut_007.pdf"
         ],
         "published": "Sat, 04 Oct 2025 10:38:06 +0000",
         "publishedParsed": "2025-10-04T10:38:06Z"
     },
     {
         "title": "Earth was born dry until a cosmic collision made it a blue planet",
         "description": "\u003ca href=\"https://news.ycombinator.com/item?id=45427972\"\u003eComments\u003c/a\u003e",
         "link": "https://www.sciencedaily.com/releases/2025/09/250928095654.htm",
         "links": [
             "https://www.sciencedaily.com/releases/2025/09/250928095654.htm"
         ],
         "published": "Tue, 30 Sep 2025 16:54:43 +0000",
         "publishedParsed": "2025-09-30T16:54:43Z"
     },
     {
         "title": "Alibaba cloud FPGA: the $200 Kintex UltraScale+",
         "description": "\u003ca href=\"https://news.ycombinator.com/item?id=45471136\"\u003eComments\u003c/a\u003e",
         "link": "https://essenceia.github.io/projects/alibaba_cloud_fpga/",
         "links": [
             "https://essenceia.github.io/projects/alibaba_cloud_fpga/"
         ],
         "published": "Sat, 04 Oct 2025 06:49:58 +0000",
         "publishedParsed": "2025-10-04T06:49:58Z"
     },
     {
         "title": "Show HN: Cobalt – a pixel-art painting studio for the Nintendo DS",
         "description": "\u003ca href=\"https://news.ycombinator.com/item?id=45431115\"\u003eComments\u003c/a\u003e",
         "link": "https://benbridle.com/projects/cobalt.html",
         "links": [
             "https://benbridle.com/projects/cobalt.html"
         ],
         "published": "Tue, 30 Sep 2025 20:54:45 +0000",
         "publishedParsed": "2025-09-30T20:54:45Z"
     },
     {
         "title": "Zig builds are getting faster",
         "description": "\u003ca href=\"https://news.ycombinator.com/item?id=45468698\"\u003eComments\u003c/a\u003e",
         "link": "https://mitchellh.com/writing/zig-builds-getting-faster",
         "links": [
             "https://mitchellh.com/writing/zig-builds-getting-faster"
         ],
         "published": "Fri, 03 Oct 2025 22:45:28 +0000",
         "publishedParsed": "2025-10-03T22:45:28Z"
     },
     {
         "title": "Offline card payments should be possible no later than 1 July 2026",
         "description": "\u003ca href=\"https://news.ycombinator.com/item?id=45467500\"\u003eComments\u003c/a\u003e",
         "link": "https://www.riksbank.se/en-gb/press-and-published/notices-and-press-releases/press-releases/2025/offline-card-payments-should-be-possible-no-later-than-1-july-2026/",
         "links": [
             "https://www.riksbank.se/en-gb/press-and-published/notices-and-press-releases/press-releases/2025/offline-card-payments-should-be-possible-no-later-than-1-july-2026/"
         ],
         "published": "Fri, 03 Oct 2025 20:36:03 +0000",
         "publishedParsed": "2025-10-03T20:36:03Z"
     },
     {
         "title": "Systems Programming with Zig",
         "description": "\u003ca href=\"https://news.ycombinator.com/item?id=45436289\"\u003eComments\u003c/a\u003e",
         "link": "https://www.manning.com/books/systems-programming-with-zig",
         "links": [
             "https://www.manning.com/books/systems-programming-with-zig"
         ],
         "published": "Wed, 01 Oct 2025 10:51:37 +0000",
         "publishedParsed": "2025-10-01T10:51:37Z"
     },
     {
         "title": "Time needed to factor large integers",
         "description": "\u003ca href=\"https://news.ycombinator.com/item?id=45429590\"\u003eComments\u003c/a\u003e",
         "link": "https://www.johndcook.com/blog/2025/09/30/time-needed-to-factor-large-integers/",
         "links": [
             "https://www.johndcook.com/blog/2025/09/30/time-needed-to-factor-large-integers/"
         ],
         "published": "Tue, 30 Sep 2025 18:53:12 +0000",
         "publishedParsed": "2025-09-30T18:53:12Z"
     },
     {
         "title": "Privacy Harm Is Harm",
         "description": "\u003ca href=\"https://news.ycombinator.com/item?id=45474441\"\u003eComments\u003c/a\u003e",
         "link": "https://www.eff.org/deeplinks/2025/10/privacy-harm-harm",
         "links": [
             "https://www.eff.org/deeplinks/2025/10/privacy-harm-harm"
         ],
         "published": "Sat, 04 Oct 2025 16:19:04 +0000",
         "publishedParsed": "2025-10-04T16:19:04Z"
     },
     {
         "title": "The Architecture of Learning: From Statistics to Intelligence",
         "description": "\u003ca href=\"https://news.ycombinator.com/item?id=45434678\"\u003eComments\u003c/a\u003e",
         "link": "https://little-book-of.github.io/maths/books/en-US/chronicles-8.html",
         "links": [
             "https://little-book-of.github.io/maths/books/en-US/chronicles-8.html"
         ],
         "published": "Wed, 01 Oct 2025 05:49:14 +0000",
         "publishedParsed": "2025-10-01T05:49:14Z"
     },
     {
         "title": "Fluid Glass",
         "description": "\u003ca href=\"https://news.ycombinator.com/item?id=45422147\"\u003eComments\u003c/a\u003e",
         "link": "https://chiuhans111.github.io/fluidglass/",
         "links": [
             "https://chiuhans111.github.io/fluidglass/"
         ],
         "published": "Tue, 30 Sep 2025 05:15:40 +0000",
         "publishedParsed": "2025-09-30T05:15:40Z"
     },
     {
         "title": "New antibiotic targets IBD and AI predicted how it would work",
         "description": "\u003ca href=\"https://news.ycombinator.com/item?id=45469579\"\u003eComments\u003c/a\u003e",
         "link": "https://healthsci.mcmaster.ca/new-antibiotic-targets-ibd-and-ai-predicted-how-it-would-work-before-scientists-could-prove-it/",
         "links": [
             "https://healthsci.mcmaster.ca/new-antibiotic-targets-ibd-and-ai-predicted-how-it-would-work-before-scientists-could-prove-it/"
         ],
         "published": "Sat, 04 Oct 2025 01:09:37 +0000",
         "publishedParsed": "2025-10-04T01:09:37Z"
     },
     {
         "title": "Where it's at://",
         "description": "\u003ca href=\"https://news.ycombinator.com/item?id=45455164\"\u003eComments\u003c/a\u003e",
         "link": "https://overreacted.io/where-its-at/",
         "links": [
             "https://overreacted.io/where-its-at/"
         ],
         "published": "Thu, 02 Oct 2025 20:31:43 +0000",
         "publishedParsed": "2025-10-02T20:31:43Z"
     },
     {
         "title": "How functional programming shaped and twisted front end development",
         "description": "\u003ca href=\"https://news.ycombinator.com/item?id=45473019\"\u003eComments\u003c/a\u003e",
         "link": "https://alfy.blog/2025/10/04/how-functional-programming-shaped-modern-frontend.html",
         "links": [
             "https://alfy.blog/2025/10/04/how-functional-programming-shaped-modern-frontend.html"
         ],
         "published": "Sat, 04 Oct 2025 13:04:15 +0000",
         "publishedParsed": "2025-10-04T13:04:15Z"
     },
     {
         "title": "BiDirectional text in the terminal emulators and console programs(2020)",
         "description": "\u003ca href=\"https://news.ycombinator.com/item?id=45434758\"\u003eComments\u003c/a\u003e",
         "link": "https://gist.github.com/XVilka/a0e49e1c65370ba11c17",
         "links": [
             "https://gist.github.com/XVilka/a0e49e1c65370ba11c17"
         ],
         "published": "Wed, 01 Oct 2025 06:03:41 +0000",
         "publishedParsed": "2025-10-01T06:03:41Z"
     },
     {
         "title": "PEP 810 – Explicit lazy imports",
         "description": "\u003ca href=\"https://news.ycombinator.com/item?id=45466086\"\u003eComments\u003c/a\u003e",
         "link": "https://pep-previews--4622.org.readthedocs.build/pep-0810/",
         "links": [
             "https://pep-previews--4622.org.readthedocs.build/pep-0810/"
         ],
         "published": "Fri, 03 Oct 2025 18:24:58 +0000",
         "publishedParsed": "2025-10-03T18:24:58Z"
     },
     {
         "title": "Old Stockholm Telephone Tower",
         "description": "\u003ca href=\"https://news.ycombinator.com/item?id=45447057\"\u003eComments\u003c/a\u003e",
         "link": "https://en.wikipedia.org/wiki/Old_Stockholm_telephone_tower",
         "links": [
             "https://en.wikipedia.org/wiki/Old_Stockholm_telephone_tower"
         ],
         "published": "Thu, 02 Oct 2025 07:12:18 +0000",
         "publishedParsed": "2025-10-02T07:12:18Z"
     },
     {
         "title": "The collapse of the econ PhD job market",
         "description": "\u003ca href=\"https://news.ycombinator.com/item?id=45464984\"\u003eComments\u003c/a\u003e",
         "link": "https://www.chrisbrunet.com/p/the-collapse-of-the-econ-phd-job",
         "links": [
             "https://www.chrisbrunet.com/p/the-collapse-of-the-econ-phd-job"
         ],
         "published": "Fri, 03 Oct 2025 16:49:57 +0000",
         "publishedParsed": "2025-10-03T16:49:57Z"
     },
     {
         "title": "Toyota runs a car-hacking event to boost security (2024)",
         "description": "\u003ca href=\"https://news.ycombinator.com/item?id=45470206\"\u003eComments\u003c/a\u003e",
         "link": "https://toyotatimes.jp/en/spotlights/1061.html",
         "links": [
             "https://toyotatimes.jp/en/spotlights/1061.html"
         ],
         "published": "Sat, 04 Oct 2025 03:11:28 +0000",
         "publishedParsed": "2025-10-04T03:11:28Z"
     },
     {
         "title": "Jules, remote coding agent from Google Labs, announces API",
         "description": "\u003ca href=\"https://news.ycombinator.com/item?id=45466588\"\u003eComments\u003c/a\u003e",
         "link": "https://jules.google/docs/changelog/",
         "links": [
             "https://jules.google/docs/changelog/"
         ],
         "published": "Fri, 03 Oct 2025 19:08:11 +0000",
         "publishedParsed": "2025-10-03T19:08:11Z"
     }
 ]