[
     {
         "title": "Not far from the clashes between agents and protesters, life goes on in Los Angeles.",
         "description": "Los Angeles County, all 4,000 square miles of it, has a way of insulating and isolating mayhem, man-made or otherwise.",
         "link": "https://www.nytimes.com/2025/06/08/us/los-angeles-clashes-ordinary-life.html",
         "links": [
             "https://www.nytimes.com/2025/06/08/us/los-angeles-clashes-ordinary-life.html"
         ],
         "published": "Mon, 09 Jun 2025 01:51:27 +0000",
         "publishedParsed": "2025-06-09T01:51:27Z",
         "author": {
             "name": "Shawn Hubler"
         },
         "authors": [
             {
                 "name": "Shawn Hubler"
             }
         ],
         "guid": "https://www.nytimes.com/2025/06/08/us/los-angeles-clashes-ordinary-life.html",
         "image": {
             "url": "https://static01.nyt.com/images/2025/06/08/multimedia/08immigration-protests-everyday-life-bpzj/08immigration-protests-everyday-life-bpzj-mediumSquareAt3X.jpg"
         },
         "categories": [
             "Los Angeles County (Calif)",
             "Demonstrations, Protests and Riots",
             "Immigration and Emigration",
             "Illegal Immigration",
             "National Guard",
             "Trump, Donald J",
             "United States Politics and Government",
             "Compton (Calif)"
         ],
         "dcExt": {
             "creator": [
                 "Shawn Hubler"
             ]
         },
         "extensions": {
             "atom": {
                 "link": [
                     {
                         "name": "link",
                         "value": "",
                         "attrs": {
                             "href": "https://www.nytimes.com/2025/06/08/us/los-angeles-clashes-ordinary-life.html",
                             "rel": "standout"
                         },
                         "children": {}
                     }
                 ]
             },
             "dc": {
                 "creator": [
                     {
                         "name": "creator",
                         "value": "Shawn Hubler",
                         "attrs": {},
                         "children": {}
                     }
                 ]
             },
             "media": {
                 "content": [
                     {
                         "name": "content",
                         "value": "",
                         "attrs": {
                             "height": "1800",
                             "medium": "image",
                             "url": "https://static01.nyt.com/images/2025/06/08/multimedia/08immigration-protests-everyday-life-bpzj/08immigration-protests-everyday-life-bpzj-mediumSquareAt3X.jpg",
                             "width": "1800"
                         },
                         "children": {}
                     }
                 ],
                 "credit": [
                     {
                         "name": "credit",
                         "value": "Blake Fagan/Agence France-Presse — Getty Images",
                         "attrs": {},
                         "children": {}
                     }
                 ],
                 "description": [
                     {
                         "name": "description",
                         "value": "The 55th Annual Los Angeles Pride Parade was held in Hollywood on Sunday.",
                         "attrs": {},
                         "children": {}
                     }
                 ]
             }
         }
     },
     {
         "title": "Tony Award Winners 2025: The Full List",
         "description": "The Tony Awards were held on Sunday at Radio City Music Hall in New York City.",
         "link": "https://www.nytimes.com/2025/06/08/theater/tony-award-winners.html",
         "links": [
             "https://www.nytimes.com/2025/06/08/theater/tony-award-winners.html"
         ],
         "published": "Mon, 09 Jun 2025 03:56:12 +0000",
         "publishedParsed": "2025-06-09T03:56:12Z",
         "author": {
             "name": "Rachel Sherman"
         },
         "authors": [
             {
                 "name": "Rachel Sherman"
             }
         ],
         "guid": "https://www.nytimes.com/2025/06/08/theater/tony-award-winners.html",
         "image": {
             "url": "https://static01.nyt.com/images/2025/06/08/multimedia/08cul-tony-winners-list-topnew2-mjzb/08cul-tony-winners-list-topnew2-mjzb-mediumSquareAt3X.jpg"
         },
         "categories": [
             "Tony Awards (Theater Awards)",
             "Theater",
             "Theater (Broadway)",
             "Actors and Actresses"
         ],
         "dcExt": {
             "creator": [
                 "Rachel Sherman"
             ]
         },
         "extensions": {
             "atom": {
                 "link": [
                     {
                         "name": "link",
                         "value": "",
                         "attrs": {
                             "href": "https://www.nytimes.com/2025/06/08/theater/tony-award-winners.html",
                             "rel": "standout"
                         },
                         "children": {}
                     }
                 ]
             },
             "dc": {
                 "creator": [
                     {
                         "name": "creator",
                         "value": "Rachel Sherman",
                         "attrs": {},
                         "children": {}
                     }
                 ]
             },
             "media": {
                 "content": [
                     {
                         "name": "content",
                         "value": "",
                         "attrs": {
                             "height": "1800",
                             "medium": "image",
                             "url": "https://static01.nyt.com/images/2025/06/08/multimedia/08cul-tony-winners-list-topnew2-mjzb/08cul-tony-winners-list-topnew2-mjzb-mediumSquareAt3X.jpg",
                             "width": "1800"
                         },
                         "children": {}
                     }
                 ],
                 "credit": [
                     {
                         "name": "credit",
                         "value": "Sara Krulwich/The New York Times",
                         "attrs": {},
                         "children": {}
                     }
                 ],
                 "description": [
                     {
                         "name": "description",
                         "value": "In a competitive race, Nicole Scherzinger won the Tony Award for best lead actress in a musical.",
                         "attrs": {},
                         "children": {}
                     }
                 ]
             }
         }
     },
     {
         "title": "Lin-Manuel Miranda and Original ‘Hamilton’ Cast Reunited for a Tonys Medley",
         "description": "Marking the 10th anniversary of the show’s opening, the creator and cast reunited to perform “My Shot,” “The Schuyler Sisters” and other notable songs.",
         "link": "https://www.nytimes.com/2025/06/08/theater/hamilton-performance-tony-awards.html",
         "links": [
             "https://www.nytimes.com/2025/06/08/theater/hamilton-performance-tony-awards.html"
         ],
         "published": "Mon, 09 Jun 2025 01:57:44 +0000",
         "publishedParsed": "2025-06-09T01:57:44Z",
         "author": {
             "name": "Michael Paulson"
         },
         "authors": [
             {
                 "name": "Michael Paulson"
             }
         ],
         "guid": "https://www.nytimes.com/2025/06/08/theater/hamilton-performance-tony-awards.html",
         "image": {
             "url": "https://static01.nyt.com/images/2025/06/08/multimedia/08tony-awards-hamilton-cvzb/08tony-awards-hamilton-cvzb-mediumSquareAt3X-v5.jpg"
         },
         "categories": [
             "Theater (Broadway)",
             "Theater",
             "Tony Awards (Theater Awards)",
             "Hamilton (Play)",
             "Miranda, Lin-Manuel",
             "Diggs, Daveed",
             "Goldsberry, Renee Elise",
             "Groff, Jonathan",
             "Jackson, Christopher (Actor)",
             "Soo, Phillipa",
             "Odom, Leslie Jr"
         ],
         "dcExt": {
             "creator": [
                 "Michael Paulson"
             ]
         },
         "extensions": {
             "atom": {
                 "link": [
                     {
                         "name": "link",
                         "value": "",
                         "attrs": {
                             "href": "https://www.nytimes.com/2025/06/08/theater/hamilton-performance-tony-awards.html",
                             "rel": "standout"
                         },
                         "children": {}
                     }
                 ]
             },
             "dc": {
                 "creator": [
                     {
                         "name": "creator",
                         "value": "Michael Paulson",
                         "attrs": {},
                         "children": {}
                     }
                 ]
             },
             "media": {
                 "content": [
                     {
                         "name": "content",
                         "value": "",
                         "attrs": {
                             "height": "1800",
                             "medium": "image",
                             "url": "https://static01.nyt.com/images/2025/06/08/multimedia/08tony-awards-hamilton-cvzb/08tony-awards-hamilton-cvzb-mediumSquareAt3X-v5.jpg",
                             "width": "1800"
                         },
                         "children": {}
                     }
                 ],
                 "credit": [
                     {
                         "name": "credit",
                         "value": "Sara Krulwich/The New York Times",
                         "attrs": {},
                         "children": {}
                     }
                 ],
                 "description": [
                     {
                         "name": "description",
                         "value": "Lin-Manuel Miranda and Leslie Odom Jr. performed a medley of “Hamilton” songs on Sunday night.",
                         "attrs": {},
                         "children": {}
                     }
                 ]
             }
         }
     },
     {
         "title": "Candid Photos from the Tony Awards Red Carpet",
         "description": "As Broadway’s best and brightest arrived for the industry’s biggest night, we got an up-close look at what you couldn’t see on TV.",
         "link": "https://www.nytimes.com/2025/06/08/theater/tonys-red-carpet-snapshots.html",
         "links": [
             "https://www.nytimes.com/2025/06/08/theater/tonys-red-carpet-snapshots.html"
         ],
         "published": "Mon, 09 Jun 2025 00:54:26 +0000",
         "publishedParsed": "2025-06-09T00:54:26Z",
         "author": {
             "name": "Sinna Nasseri"
         },
         "authors": [
             {
                 "name": "Sinna Nasseri"
             }
         ],
         "guid": "https://www.nytimes.com/2025/06/08/theater/tonys-red-carpet-snapshots.html",
         "image": {
             "url": "https://static01.nyt.com/images/2025/06/08/multimedia/08CUL-TONYS-CARPET-PHOTOS-SNOOK-wlvm/08CUL-TONYS-CARPET-PHOTOS-SNOOK-wlvm-mediumSquareAt3X-v5.jpg"
         },
         "categories": [
             "Theater",
             "Tony Awards (Theater Awards)"
         ],
         "dcExt": {
             "creator": [
                 "Sinna Nasseri"
             ]
         },
         "extensions": {
             "atom": {
                 "link": [
                     {
                         "name": "link",
                         "value": "",
                         "attrs": {
                             "href": "https://www.nytimes.com/2025/06/08/theater/tonys-red-carpet-snapshots.html",
                             "rel": "standout"
                         },
                         "children": {}
                     }
                 ]
             },
             "dc": {
                 "creator": [
                     {
                         "name": "creator",
                         "value": "Sinna Nasseri",
                         "attrs": {},
                         "children": {}
                     }
                 ]
             },
             "media": {
                 "content": [
                     {
                         "name": "content",
                         "value": "",
                         "attrs": {
                             "height": "1000",
                             "medium": "image",
                             "url": "https://static01.nyt.com/images/2025/06/08/multimedia/08CUL-TONYS-CARPET-PHOTOS-SNOOK-wlvm/08CUL-TONYS-CARPET-PHOTOS-SNOOK-wlvm-mediumSquareAt3X-v5.jpg",
                             "width": "1000"
                         },
                         "children": {}
                     }
                 ]
             }
         }
     },
     {
         "title": "Touring a Tunnel in Gaza That Leads Underneath a Hospital",
         "description": "To Israelis, the location of an underground passageway highlights Hamas’s abuse of civilians. To Palestinians, Israel’s decision to target it highlights Israel’s own disregard for civilian life.",
         "link": "https://www.nytimes.com/2025/06/08/world/middleeast/gaza-hospital-tunnel.html",
         "links": [
             "https://www.nytimes.com/2025/06/08/world/middleeast/gaza-hospital-tunnel.html"
         ],
         "published": "Sun, 08 Jun 2025 21:49:09 +0000",
         "publishedParsed": "2025-06-08T21:49:09Z",
         "author": {
             "name": "Patrick Kingsley"
         },
         "authors": [
             {
                 "name": "Patrick Kingsley"
             }
         ],
         "guid": "https://www.nytimes.com/2025/06/08/world/middleeast/gaza-hospital-tunnel.html",
         "image": {
             "url": "https://static01.nyt.com/images/2025/06/08/multimedia/08int-gaza-tunnel01-photo-bhmc/08int-gaza-tunnel01-photo-bhmc-mediumSquareAt3X.jpg"
         },
         "categories": [
             "European Hospital (Gaza Strip)",
             "Hamas",
             "Israel",
             "Defense and Military Forces",
             "Israel-Gaza War (2023- )",
             "Bridges and Tunnels",
             "Gaza Strip",
             "Hospitals",
             "Palestinians"
         ],
         "dcExt": {
             "creator": [
                 "Patrick Kingsley"
             ]
         },
         "extensions": {
             "atom": {
                 "link": [
                     {
                         "name": "link",
                         "value": "",
                         "attrs": {
                             "href": "https://www.nytimes.com/2025/06/08/world/middleeast/gaza-hospital-tunnel.html",
                             "rel": "standout"
                         },
                         "children": {}
                     }
                 ]
             },
             "dc": {
                 "creator": [
                     {
                         "name": "creator",
                         "value": "Patrick Kingsley",
                         "attrs": {},
                         "children": {}
                     }
                 ]
             },
             "media": {
                 "content": [
                     {
                         "name": "content",
                         "value": "",
                         "attrs": {
                             "height": "1800",
                             "medium": "image",
                             "url": "https://static01.nyt.com/images/2025/06/08/multimedia/08int-gaza-tunnel01-photo-bhmc/08int-gaza-tunnel01-photo-bhmc-mediumSquareAt3X.jpg",
                             "width": "1800"
                         },
                         "children": {}
                     }
                 ],
                 "credit": [
                     {
                         "name": "credit",
                         "value": "Patrick Kingsley/The New York Times",
                         "attrs": {},
                         "children": {}
                     }
                 ],
                 "description": [
                     {
                         "name": "description",
                         "value": "A tunnel near a major hospital in southern Gaza that leads to a tiny room where the Israeli military says a top Hamas militant commander was killed.",
                         "attrs": {},
                         "children": {}
                     }
                 ]
             }
         }
     },
     {
         "title": "For Decades of N.B.A. Finals, This Photographer Has Been Courtside",
         "description": "The photographer Nathaniel Butler reflects on his enduring images of stars like Bill Russell, Michael Jordan and Kobe Bryant.",
         "link": "https://www.nytimes.com/2025/06/06/arts/design/nba-finals-nathaniel-butler-photographs.html",
         "links": [
             "https://www.nytimes.com/2025/06/06/arts/design/nba-finals-nathaniel-butler-photographs.html"
         ],
         "published": "Fri, 06 Jun 2025 09:00:20 +0000",
         "publishedParsed": "2025-06-06T09:00:20Z",
         "author": {
             "name": "Emmanuel Morgan"
         },
         "authors": [
             {
                 "name": "Emmanuel Morgan"
             }
         ],
         "guid": "https://www.nytimes.com/2025/06/06/arts/design/nba-finals-nathaniel-butler-photographs.html",
         "categories": [
             "Photography",
             "Basketball",
             "NBA Championship",
             "National Basketball Assn",
             "Butler, Nathaniel S (Photographer)",
             "Allen, Ray (1975- )",
             "Bryant, Kobe",
             "James, LeBron",
             "Johnson, Earvin",
             "Jordan, Michael",
             "Popovich, Gregg",
             "Tatum, Jayson (1998- )",
             "Russell, William Felton (1934- )"
         ],
         "dcExt": {
             "creator": [
                 "Emmanuel Morgan"
             ]
         },
         "extensions": {
             "atom": {
                 "link": [
                     {
                         "name": "link",
                         "value": "",
                         "attrs": {
                             "href": "https://www.nytimes.com/2025/06/06/arts/design/nba-finals-nathaniel-butler-photographs.html",
                             "rel": "standout"
                         },
                         "children": {}
                     }
                 ]
             },
             "dc": {
                 "creator": [
                     {
                         "name": "creator",
                         "value": "Emmanuel Morgan",
                         "attrs": {},
                         "children": {}
                     }
                 ]
             }
         }
     },
     {
         "title": "Hong Kong Looks for Ways to Win Back Big-Spending Tourists",
         "description": "A city with an image dented by protests, pandemic restrictions and a security crackdown hopes to broaden its appeal beyond budget-minded visitors from mainland China.",
         "link": "https://www.nytimes.com/2025/06/07/world/asia/00int-hongkong-china-tourists.html",
         "links": [
             "https://www.nytimes.com/2025/06/07/world/asia/00int-hongkong-china-tourists.html"
         ],
         "published": "Sun, 08 Jun 2025 04:03:55 +0000",
         "publishedParsed": "2025-06-08T04:03:55Z",
         "author": {
             "name": "Tiffany May"
         },
         "authors": [
             {
                 "name": "Tiffany May"
             }
         ],
         "guid": "https://www.nytimes.com/2025/06/07/world/asia/00int-hongkong-china-tourists.html",
         "image": {
             "url": "https://static01.nyt.com/images/2025/05/27/multimedia/00int-hongkong-tourism-01-phzw/00int-hongkong-tourism-01-phzw-mediumSquareAt3X.jpg"
         },
         "categories": [
             "Hong Kong",
             "Travel and Vacations",
             "Politics and Government",
             "China",
             "Travel Warnings",
             "Gross Domestic Product",
             "Luxury Goods and Services",
             "Coldplay (Music Group)",
             "Formula One",
             "Manchester United (Soccer Team)",
             "Ferris Wheels",
             "Pop and Rock Music"
         ],
         "dcExt": {
             "creator": [
                 "Tiffany May"
             ]
         },
         "extensions": {
             "atom": {
                 "link": [
                     {
                         "name": "link",
                         "value": "",
                         "attrs": {
                             "href": "https://www.nytimes.com/2025/06/07/world/asia/00int-hongkong-china-tourists.html",
                             "rel": "standout"
                         },
                         "children": {}
                     }
                 ]
             },
             "dc": {
                 "creator": [
                     {
                         "name": "creator",
                         "value": "Tiffany May",
                         "attrs": {},
                         "children": {}
                     }
                 ]
             },
             "media": {
                 "content": [
                     {
                         "name": "content",
                         "value": "",
                         "attrs": {
                             "height": "1798",
                             "medium": "image",
                             "url": "https://static01.nyt.com/images/2025/05/27/multimedia/00int-hongkong-tourism-01-phzw/00int-hongkong-tourism-01-phzw-mediumSquareAt3X.jpg",
                             "width": "1800"
                         },
                         "children": {}
                     }
                 ],
                 "credit": [
                     {
                         "name": "credit",
                         "value": "Anthony Kwan for The New York Times",
                         "attrs": {},
                         "children": {}
                     }
                 ],
                 "description": [
                     {
                         "name": "description",
                         "value": "People heading into the new Kai Tak Stadium in Hong Kong. The city is seeking to rebrand itself as the region’s events capital, emphasizing concerts and trade shows.",
                         "attrs": {},
                         "children": {}
                     }
                 ]
             }
         }
     },
     {
         "title": "4 Injured as Skydiving Plane Crashes in Tennessee",
         "description": "The plane, which had 20 people on board, crashed on Sunday afternoon. Four people were injured, one critically, officials said.",
         "link": "https://www.nytimes.com/2025/06/08/us/plane-crash-tennessee.html",
         "links": [
             "https://www.nytimes.com/2025/06/08/us/plane-crash-tennessee.html"
         ],
         "published": "Sun, 08 Jun 2025 22:06:05 +0000",
         "publishedParsed": "2025-06-08T22:06:05Z",
         "author": {
             "name": "Mark Walker"
         },
         "authors": [
             {
                 "name": "Mark Walker"
             }
         ],
         "guid": "https://www.nytimes.com/2025/06/08/us/plane-crash-tennessee.html",
         "categories": [
             "Aviation Accidents, Safety and Disasters",
             "Airlines and Airplanes",
             "Tennessee"
         ],
         "dcExt": {
             "creator": [
                 "Mark Walker"
             ]
         },
         "extensions": {
             "atom": {
                 "link": [
                     {
                         "name": "link",
                         "value": "",
                         "attrs": {
                             "href": "https://www.nytimes.com/2025/06/08/us/plane-crash-tennessee.html",
                             "rel": "standout"
                         },
                         "children": {}
                     }
                 ]
             },
             "dc": {
                 "creator": [
                     {
                         "name": "creator",
                         "value": "Mark Walker",
                         "attrs": {},
                         "children": {}
                     }
                 ]
             }
         }
     },
     {
         "title": "Salmonella Outbreak Linked to Eggs Sickens Dozens",
         "description": "The outbreak has been tied to multiple brown organic and brown cage-free egg brands distributed to grocery stores in seven states, officials said.",
         "link": "https://www.nytimes.com/2025/06/08/health/eggs-salmonella-recall.html",
         "links": [
             "https://www.nytimes.com/2025/06/08/health/eggs-salmonella-recall.html"
         ],
         "published": "Sun, 08 Jun 2025 17:45:06 +0000",
         "publishedParsed": "2025-06-08T17:45:06Z",
         "author": {
             "name": "Johnny Diaz"
         },
         "authors": [
             {
                 "name": "Johnny Diaz"
             }
         ],
         "guid": "https://www.nytimes.com/2025/06/08/health/eggs-salmonella-recall.html",
         "image": {
             "url": "https://static01.nyt.com/images/2025/06/08/multimedia/08xp-eggs-bhft/08xp-eggs-bhft-mediumSquareAt3X.jpg"
         },
         "categories": [
             "Eggs",
             "Recalls and Bans of Products",
             "Salmonella (Bacteria)",
             "Food Contamination and Poisoning",
             "Walmart Stores Inc",
             "Centers for Disease Control and Prevention",
             "Food and Drug Administration",
             "Arizona",
             "California",
             "Supermarkets and Grocery Stores"
         ],
         "dcExt": {
             "creator": [
                 "Johnny Diaz"
             ]
         },
         "extensions": {
             "atom": {
                 "link": [
                     {
                         "name": "link",
                         "value": "",
                         "attrs": {
                             "href": "https://www.nytimes.com/2025/06/08/health/eggs-salmonella-recall.html",
                             "rel": "standout"
                         },
                         "children": {}
                     }
                 ]
             },
             "dc": {
                 "creator": [
                     {
                         "name": "creator",
                         "value": "Johnny Diaz",
                         "attrs": {},
                         "children": {}
                     }
                 ]
             },
             "media": {
                 "content": [
                     {
                         "name": "content",
                         "value": "",
                         "attrs": {
                             "height": "1800",
                             "medium": "image",
                             "url": "https://static01.nyt.com/images/2025/06/08/multimedia/08xp-eggs-bhft/08xp-eggs-bhft-mediumSquareAt3X.jpg",
                             "width": "1800"
                         },
                         "children": {}
                     }
                 ],
                 "credit": [
                     {
                         "name": "credit",
                         "value": "Sam Mircovich/Reuters",
                         "attrs": {},
                         "children": {}
                     }
                 ],
                 "description": [
                     {
                         "name": "description",
                         "value": "Seventy-nine people have gotten ill from the outbreak linked to the eggs, and 21 people have been hospitalized, according to the U.S. Centers for Disease Control and Prevention.",
                         "attrs": {},
                         "children": {}
                     }
                 ]
             }
         }
     },
     {
         "title": "The Rich Compensation for Being the C.E.O.",
         "description": "The chief executives at Palantir, which scoops up data for the government, and Veeva Systems, a cloud-computing company, topped two lists of the highest-paid C.E.O.s.",
         "link": "https://www.nytimes.com/2025/06/06/business/highest-paid-ceos.html",
         "links": [
             "https://www.nytimes.com/2025/06/06/business/highest-paid-ceos.html"
         ],
         "published": "Fri, 06 Jun 2025 19:46:00 +0000",
         "publishedParsed": "2025-06-06T19:46:00Z",
         "author": {
             "name": "Jeff Sommer"
         },
         "authors": [
             {
                 "name": "Jeff Sommer"
             }
         ],
         "guid": "https://www.nytimes.com/2025/06/06/business/highest-paid-ceos.html",
         "image": {
             "url": "https://static01.nyt.com/images/2025/06/08/business/08Exec-Pay-illo/08Exec-Pay-illo-mediumSquareAt3X.jpg"
         },
         "categories": [
             "Executive Compensation",
             "Wages and Salaries",
             "Income Inequality",
             "Dodd-Frank Wall Street Reform and Consumer Protection Act (2010)",
             "Karp, Alex",
             "Palantir Technologies",
             "United States",
             "Veeva Systems Inc",
             "Gassner, Peter"
         ],
         "dcExt": {
             "creator": [
                 "Jeff Sommer"
             ]
         },
         "extensions": {
             "atom": {
                 "link": [
                     {
                         "name": "link",
                         "value": "",
                         "attrs": {
                             "href": "https://www.nytimes.com/2025/06/06/business/highest-paid-ceos.html",
                             "rel": "standout"
                         },
                         "children": {}
                     }
                 ]
             },
             "dc": {
                 "creator": [
                     {
                         "name": "creator",
                         "value": "Jeff Sommer",
                         "attrs": {},
                         "children": {}
                     }
                 ]
             },
             "media": {
                 "content": [
                     {
                         "name": "content",
                         "value": "",
                         "attrs": {
                             "height": "1800",
                             "medium": "image",
                             "url": "https://static01.nyt.com/images/2025/06/08/business/08Exec-Pay-illo/08Exec-Pay-illo-mediumSquareAt3X.jpg",
                             "width": "1800"
                         },
                         "children": {}
                     }
                 ],
                 "credit": [
                     {
                         "name": "credit",
                         "value": "Nicolas Ortega",
                         "attrs": {},
                         "children": {}
                     }
                 ]
             }
         }
     },
     {
         "title": "Women in Berlin allowed to swim topless in public pools, just like men",
         "content": "\u0026#32; submitted by \u0026#32; \u003ca href=\"https://www.reddit.com/user/arseflare\"\u003e /u/arseflare \u003c/a\u003e \u003cbr/\u003e \u003cspan\u003e\u003ca href=\"https://www.cnn.com/travel/article/berlin-public-swimming-pools-intl\"\u003e[link]\u003c/a\u003e\u003c/span\u003e \u0026#32; \u003cspan\u003e\u003ca href=\"https://www.reddit.com/r/news/comments/1l6tj6p/women_in_berlin_allowed_to_swim_topless_in_public/\"\u003e[comments]\u003c/a\u003e\u003c/span\u003e",
         "link": "https://www.reddit.com/r/news/comments/1l6tj6p/women_in_berlin_allowed_to_swim_topless_in_public/",
         "links": [
             "https://www.reddit.com/r/news/comments/1l6tj6p/women_in_berlin_allowed_to_swim_topless_in_public/"
         ],
         "updated": "2025-06-09T02:22:16+00:00",
         "updatedParsed": "2025-06-09T02:22:16Z",
         "published": "2025-06-09T02:22:16+00:00",
         "publishedParsed": "2025-06-09T02:22:16Z",
         "author": {
             "name": "/u/arseflare"
         },
         "authors": [
             {
                 "name": "/u/arseflare"
             }
         ],
         "guid": "t3_1l6tj6p",
         "categories": [
             "r/news"
         ]
     },
     {
         "title": "US measles cases nearing 30-year high",
         "content": "\u0026#32; submitted by \u0026#32; \u003ca href=\"https://www.reddit.com/user/StupendousMan1995\"\u003e /u/StupendousMan1995 \u003c/a\u003e \u003cbr/\u003e \u003cspan\u003e\u003ca href=\"https://abcnews.go.com/Health/us-measles-cases-nearing-30-year-high-us/story?id=122581810\"\u003e[link]\u003c/a\u003e\u003c/span\u003e \u0026#32; \u003cspan\u003e\u003ca href=\"https://www.reddit.com/r/news/comments/1l6t5gr/us_measles_cases_nearing_30year_high/\"\u003e[comments]\u003c/a\u003e\u003c/span\u003e",
         "link": "https://www.reddit.com/r/news/comments/1l6t5gr/us_measles_cases_nearing_30year_high/",
         "links": [
             "https://www.reddit.com/r/news/comments/1l6t5gr/us_measles_cases_nearing_30year_high/"
         ],
         "updated": "2025-06-09T02:02:37+00:00",
         "updatedParsed": "2025-06-09T02:02:37Z",
         "published": "2025-06-09T02:02:37+00:00",
         "publishedParsed": "2025-06-09T02:02:37Z",
         "author": {
             "name": "/u/StupendousMan1995"
         },
         "authors": [
             {
                 "name": "/u/StupendousMan1995"
             }
         ],
         "guid": "t3_1l6t5gr",
         "categories": [
             "r/news"
         ]
     },
     {
         "title": "Nine women accuse Jared Leto of sexual impropriety in new report",
         "content": "\u0026#32; submitted by \u0026#32; \u003ca href=\"https://www.reddit.com/user/untamedlazyeye\"\u003e /u/untamedlazyeye \u003c/a\u003e \u003cbr/\u003e \u003cspan\u003e\u003ca href=\"https://www.theguardian.com/film/2025/jun/07/jared-leto-accused-sexual-impropriety\"\u003e[link]\u003c/a\u003e\u003c/span\u003e \u0026#32; \u003cspan\u003e\u003ca href=\"https://www.reddit.com/r/news/comments/1l6cqha/nine_women_accuse_jared_leto_of_sexual/\"\u003e[comments]\u003c/a\u003e\u003c/span\u003e",
         "link": "https://www.reddit.com/r/news/comments/1l6cqha/nine_women_accuse_jared_leto_of_sexual/",
         "links": [
             "https://www.reddit.com/r/news/comments/1l6cqha/nine_women_accuse_jared_leto_of_sexual/"
         ],
         "updated": "2025-06-08T13:55:43+00:00",
         "updatedParsed": "2025-06-08T13:55:43Z",
         "published": "2025-06-08T13:55:43+00:00",
         "publishedParsed": "2025-06-08T13:55:43Z",
         "author": {
             "name": "/u/untamedlazyeye"
         },
         "authors": [
             {
                 "name": "/u/untamedlazyeye"
             }
         ],
         "guid": "t3_1l6cqha",
         "categories": [
             "r/news"
         ]
     },
     {
         "title": "Runaway zebra named Ed caught after a week on the run in Tennessee",
         "content": "\u0026#32; submitted by \u0026#32; \u003ca href=\"https://www.reddit.com/user/No_Idea_Guy\"\u003e /u/No_Idea_Guy \u003c/a\u003e \u003cbr/\u003e \u003cspan\u003e\u003ca href=\"https://www.cbsnews.com/news/runaway-zebra-ed-caught-tennessee/\"\u003e[link]\u003c/a\u003e\u003c/span\u003e \u0026#32; \u003cspan\u003e\u003ca href=\"https://www.reddit.com/r/news/comments/1l6ngbv/runaway_zebra_named_ed_caught_after_a_week_on_the/\"\u003e[comments]\u003c/a\u003e\u003c/span\u003e",
         "link": "https://www.reddit.com/r/news/comments/1l6ngbv/runaway_zebra_named_ed_caught_after_a_week_on_the/",
         "links": [
             "https://www.reddit.com/r/news/comments/1l6ngbv/runaway_zebra_named_ed_caught_after_a_week_on_the/"
         ],
         "updated": "2025-06-08T21:30:05+00:00",
         "updatedParsed": "2025-06-08T21:30:05Z",
         "published": "2025-06-08T21:30:05+00:00",
         "publishedParsed": "2025-06-08T21:30:05Z",
         "author": {
             "name": "/u/No_Idea_Guy"
         },
         "authors": [
             {
                 "name": "/u/No_Idea_Guy"
             }
         ],
         "guid": "t3_1l6ngbv",
         "categories": [
             "r/news"
         ]
     },
     {
         "title": "At least 16 on plane that crashed in Tennessee, highway patrol says",
         "content": "\u0026#32; submitted by \u0026#32; \u003ca href=\"https://www.reddit.com/user/Sctvman\"\u003e /u/Sctvman \u003c/a\u003e \u003cbr/\u003e \u003cspan\u003e\u003ca href=\"https://www.cnn.com/2025/06/08/us/coffee-county-tennessee-plane-crash?cid=ios_app\"\u003e[link]\u003c/a\u003e\u003c/span\u003e \u0026#32; \u003cspan\u003e\u003ca href=\"https://www.reddit.com/r/news/comments/1l6kdwg/at_least_16_on_plane_that_crashed_in_tennessee/\"\u003e[comments]\u003c/a\u003e\u003c/span\u003e",
         "link": "https://www.reddit.com/r/news/comments/1l6kdwg/at_least_16_on_plane_that_crashed_in_tennessee/",
         "links": [
             "https://www.reddit.com/r/news/comments/1l6kdwg/at_least_16_on_plane_that_crashed_in_tennessee/"
         ],
         "updated": "2025-06-08T19:18:26+00:00",
         "updatedParsed": "2025-06-08T19:18:26Z",
         "published": "2025-06-08T19:18:26+00:00",
         "publishedParsed": "2025-06-08T19:18:26Z",
         "author": {
             "name": "/u/Sctvman"
         },
         "authors": [
             {
                 "name": "/u/Sctvman"
             }
         ],
         "guid": "t3_1l6kdwg",
         "categories": [
             "r/news"
         ]
     },
     {
         "title": "Salmonella outbreak tied to eggs makes dozens sick across 7 states in the West and Midwest",
         "content": "\u0026#32; submitted by \u0026#32; \u003ca href=\"https://www.reddit.com/user/blairb03\"\u003e /u/blairb03 \u003c/a\u003e \u003cbr/\u003e \u003cspan\u003e\u003ca href=\"https://www.cbsnews.com/news/salmonella-outbreak-tied-to-eggs-makes-cdc/\"\u003e[link]\u003c/a\u003e\u003c/span\u003e \u0026#32; \u003cspan\u003e\u003ca href=\"https://www.reddit.com/r/news/comments/1l6tas5/salmonella_outbreak_tied_to_eggs_makes_dozens/\"\u003e[comments]\u003c/a\u003e\u003c/span\u003e",
         "link": "https://www.reddit.com/r/news/comments/1l6tas5/salmonella_outbreak_tied_to_eggs_makes_dozens/",
         "links": [
             "https://www.reddit.com/r/news/comments/1l6tas5/salmonella_outbreak_tied_to_eggs_makes_dozens/"
         ],
         "updated": "2025-06-09T02:10:17+00:00",
         "updatedParsed": "2025-06-09T02:10:17Z",
         "published": "2025-06-09T02:10:17+00:00",
         "publishedParsed": "2025-06-09T02:10:17Z",
         "author": {
             "name": "/u/blairb03"
         },
         "authors": [
             {
                 "name": "/u/blairb03"
             }
         ],
         "guid": "t3_1l6tas5",
         "categories": [
             "r/news"
         ]
     },
     {
         "title": "A missed drop-off and tragedy at a campground. How a manhunt for a father accused of killing his 3 daughters is unfolding",
         "content": "\u0026#32; submitted by \u0026#32; \u003ca href=\"https://www.reddit.com/user/Blockhead47\"\u003e /u/Blockhead47 \u003c/a\u003e \u003cbr/\u003e \u003cspan\u003e\u003ca href=\"https://www.cnn.com/2025/06/08/us/travis-decker-daughters-washington-manhunt\"\u003e[link]\u003c/a\u003e\u003c/span\u003e \u0026#32; \u003cspan\u003e\u003ca href=\"https://www.reddit.com/r/news/comments/1l6p5r5/a_missed_dropoff_and_tragedy_at_a_campground_how/\"\u003e[comments]\u003c/a\u003e\u003c/span\u003e",
         "link": "https://www.reddit.com/r/news/comments/1l6p5r5/a_missed_dropoff_and_tragedy_at_a_campground_how/",
         "links": [
             "https://www.reddit.com/r/news/comments/1l6p5r5/a_missed_dropoff_and_tragedy_at_a_campground_how/"
         ],
         "updated": "2025-06-08T22:46:53+00:00",
         "updatedParsed": "2025-06-08T22:46:53Z",
         "published": "2025-06-08T22:46:53+00:00",
         "publishedParsed": "2025-06-08T22:46:53Z",
         "author": {
             "name": "/u/Blockhead47"
         },
         "authors": [
             {
                 "name": "/u/Blockhead47"
             }
         ],
         "guid": "t3_1l6p5r5",
         "categories": [
             "r/news"
         ]
     },
     {
         "title": "Midea recalls 1.7 million air conditioners over potential mold risk",
         "content": "\u0026#32; submitted by \u0026#32; \u003ca href=\"https://www.reddit.com/user/Keikobad\"\u003e /u/Keikobad \u003c/a\u003e \u003cbr/\u003e \u003cspan\u003e\u003ca href=\"https://www.cbsnews.com/news/midea-air-conditioner-recall-mold/\"\u003e[link]\u003c/a\u003e\u003c/span\u003e \u0026#32; \u003cspan\u003e\u003ca href=\"https://www.reddit.com/r/news/comments/1l6durs/midea_recalls_17_million_air_conditioners_over/\"\u003e[comments]\u003c/a\u003e\u003c/span\u003e",
         "link": "https://www.reddit.com/r/news/comments/1l6durs/midea_recalls_17_million_air_conditioners_over/",
         "links": [
             "https://www.reddit.com/r/news/comments/1l6durs/midea_recalls_17_million_air_conditioners_over/"
         ],
         "updated": "2025-06-08T14:45:15+00:00",
         "updatedParsed": "2025-06-08T14:45:15Z",
         "published": "2025-06-08T14:45:15+00:00",
         "publishedParsed": "2025-06-08T14:45:15Z",
         "author": {
             "name": "/u/Keikobad"
         },
         "authors": [
             {
                 "name": "/u/Keikobad"
             }
         ],
         "guid": "t3_1l6durs",
         "categories": [
             "r/news"
         ]
     },
     {
         "title": "Salmonella outbreak tied to eggs sickens dozens across 7 states",
         "content": "\u0026#32; submitted by \u0026#32; \u003ca href=\"https://www.reddit.com/user/cigr\"\u003e /u/cigr \u003c/a\u003e \u003cbr/\u003e \u003cspan\u003e\u003ca href=\"https://apnews.com/article/salmonella-outbreak-eggs-cdc-c521525f7af5d5abe50c62c98b1e082c\"\u003e[link]\u003c/a\u003e\u003c/span\u003e \u0026#32; \u003cspan\u003e\u003ca href=\"https://www.reddit.com/r/news/comments/1l5so0z/salmonella_outbreak_tied_to_eggs_sickens_dozens/\"\u003e[comments]\u003c/a\u003e\u003c/span\u003e",
         "link": "https://www.reddit.com/r/news/comments/1l5so0z/salmonella_outbreak_tied_to_eggs_sickens_dozens/",
         "links": [
             "https://www.reddit.com/r/news/comments/1l5so0z/salmonella_outbreak_tied_to_eggs_sickens_dozens/"
         ],
         "updated": "2025-06-07T19:11:30+00:00",
         "updatedParsed": "2025-06-07T19:11:30Z",
         "published": "2025-06-07T19:11:30+00:00",
         "publishedParsed": "2025-06-07T19:11:30Z",
         "author": {
             "name": "/u/cigr"
         },
         "authors": [
             {
                 "name": "/u/cigr"
             }
         ],
         "guid": "t3_1l5so0z",
         "categories": [
             "r/news"
         ]
     },
     {
         "title": "19-year-old dead after doing ’dusting’ trend seen on social media, family says",
         "content": "\u0026#32; submitted by \u0026#32; \u003ca href=\"https://www.reddit.com/user/bendubberley_\"\u003e /u/bendubberley_ \u003c/a\u003e \u003cbr/\u003e \u003cspan\u003e\u003ca href=\"https://www.knopnews2.com/2025/06/06/19-year-old-dead-after-doing-dusting-trend-that-is-seen-social-media-family-says/?outputType\"\u003e[link]\u003c/a\u003e\u003c/span\u003e \u0026#32; \u003cspan\u003e\u003ca href=\"https://www.reddit.com/r/news/comments/1l5lcaj/19yearold_dead_after_doing_dusting_trend_seen_on/\"\u003e[comments]\u003c/a\u003e\u003c/span\u003e",
         "link": "https://www.reddit.com/r/news/comments/1l5lcaj/19yearold_dead_after_doing_dusting_trend_seen_on/",
         "links": [
             "https://www.reddit.com/r/news/comments/1l5lcaj/19yearold_dead_after_doing_dusting_trend_seen_on/"
         ],
         "updated": "2025-06-07T13:52:20+00:00",
         "updatedParsed": "2025-06-07T13:52:20Z",
         "published": "2025-06-07T13:52:20+00:00",
         "publishedParsed": "2025-06-07T13:52:20Z",
         "author": {
             "name": "/u/bendubberley_"
         },
         "authors": [
             {
                 "name": "/u/bendubberley_"
             }
         ],
         "guid": "t3_1l5lcaj",
         "categories": [
             "r/news"
         ]
     },
     {
         "title": "Coco Gauff wins French Open with thrilling comeback against world No. 1 Aryna Sabalenka in women’s final",
         "content": "\u0026#32; submitted by \u0026#32; \u003ca href=\"https://www.reddit.com/user/DrLager\"\u003e /u/DrLager \u003c/a\u003e \u003cbr/\u003e \u003cspan\u003e\u003ca href=\"https://www.cnn.com/2025/06/07/sport/coco-gauff-aryna-sabalenka-french-open-final-spt\"\u003e[link]\u003c/a\u003e\u003c/span\u003e \u0026#32; \u003cspan\u003e\u003ca href=\"https://www.reddit.com/r/news/comments/1l5ohen/coco_gauff_wins_french_open_with_thrilling/\"\u003e[comments]\u003c/a\u003e\u003c/span\u003e",
         "link": "https://www.reddit.com/r/news/comments/1l5ohen/coco_gauff_wins_french_open_with_thrilling/",
         "links": [
             "https://www.reddit.com/r/news/comments/1l5ohen/coco_gauff_wins_french_open_with_thrilling/"
         ],
         "updated": "2025-06-07T16:11:46+00:00",
         "updatedParsed": "2025-06-07T16:11:46Z",
         "published": "2025-06-07T16:11:46+00:00",
         "publishedParsed": "2025-06-07T16:11:46Z",
         "author": {
             "name": "/u/DrLager"
         },
         "authors": [
             {
                 "name": "/u/DrLager"
             }
         ],
         "guid": "t3_1l5ohen",
         "categories": [
             "r/news"
         ]
     },
     {
         "title": "Powerful 6.3 magnitude earthquake shakes central Colombia - CBS News",
         "description": "\u003col\u003e\u003cli\u003e\u003ca href=\"https://news.google.com/rss/articles/CBMieEFVX3lxTE5OYlZXSy1NNk95Vk5ETS1neHZ0YlRPZmFOOXNucUJCMDMyQkMwWFk4ZkgzNWE1Q1NzUHNJWmZmVGp6YzFmT0gyeC00Sk9QcmZOX0pldEJjbWczRExTRFJUVnFFQXdUd1AxT3p2bmZmV05uRW9QcDdTYdIBfkFVX3lxTE9hWUl1VkVadUV3U0swVTQtU09zXzBaX3BuWEVkQnlySk1TQ200UkdtYl9YSmx4TGFQeWw4OUdtZEo0dUlSenFEakhxNnhQT2RTZmt5RDJvNjVRNGprclVFV1BwTDFBY0daU3RGOHBQdlFKakpzbW13WnFMa0tGQQ?oc=5\" target=\"_blank\"\u003ePowerful 6.3 magnitude earthquake shakes central Colombia\u003c/a\u003e\u0026nbsp;\u0026nbsp;\u003cfont color=\"#6f6f6f\"\u003eCBS News\u003c/font\u003e\u003c/li\u003e\u003cli\u003e\u003ca href=\"https://news.google.com/rss/articles/CBMivwFBVV95cUxNM2ozWTc3RnJ2cUV0OFRNNlVFUDg5bXYtM3NWR2RfMHZETEg1aFBtMktRSzZzUVcxaE5lZ0VQNV9vN2JrNDJsR3NKVXhYTnlGSE9FUVZYR0VLUGF3Rkc4ZGwwWC1iTVQ4eEpEc2FDS1Rkekt4SEV5OWt0d1Z6VHNNRE5Kb2kybjNNUXhPd2hpMjdFMDJRRHRpR251MlY1ZElITmxGZmwtR3BSalNhMkxnU3VLdGUzS0REeEE3MndBd9IBxAFBVV95cUxQY0ZfTGN5bFc5TWdVMmM4eEZEU21INXdyc1dHQUs0NTU0dF9MTlJ6NFBUT2JGUGxvN3EteGxvYUR2TXRHU29Oanl2VDBPa08wUTlqUXhLbTBkdEd6clJyZmtKWUFaMnJoMjNJRzdCdXhKVkdIZExyX3l0bm5hU0FSa2Myckl2Y2ZacXZQNU04bXQwUW1mbGR2OG4zWUZ4MFhRUHpqSlJBdEtLM1FaaVhqeWlVX1Mzbl9UZnBLX2lyX2xIN3Zo?oc=5\" target=\"_blank\"\u003eA 6.3 magnitude earthquake hits central Colombia, with no casualties reported\u003c/a\u003e\u0026nbsp;\u0026nbsp;\u003cfont color=\"#6f6f6f\"\u003eABC News\u003c/font\u003e\u003c/li\u003e\u003cli\u003e\u003ca href=\"https://news.google.com/rss/articles/CBMipAFBVV95cUxNWkY4aEVqbHJkS09Kbnh4b1MtQ0Zpcm0wbkJIXzdsTlF2UEhVbjRSblRiUzJkNzBweEJDZkd1SXRIQy04bnR3b183c0xwa1JqOEVpc1hkeHZrRDR1SHJaMkx2YlVtaV9sTlhKSFdKRVJvdjZzYmhVdnh2dUpqVjZoN0xpR0xKNk95TjluNWNIdUlUS3c1SkM4bU96VklqdW9rUndyOQ?oc=5\" target=\"_blank\"\u003e6.5 magnitude earthquake strikes Colombia\u003c/a\u003e\u0026nbsp;\u0026nbsp;\u003cfont color=\"#6f6f6f\"\u003eEuronews.com\u003c/font\u003e\u003c/li\u003e\u003cli\u003e\u003ca href=\"https://news.google.com/rss/articles/CBMi8AFBVV95cUxNR3VPWmVGTjJUYzFHeFdLSTRwQUlPdmJkamEtUGRrQnlZOEFSVUR1ZG1SR0NVMHZqbFV1QXZSZWpsa013TjJTMHdMSHdtRzMxdWpMVXZaMF9maVJrUU11QUFIX3Fpa3Z3S0ktU3pKRE5qQkw3X0JDSUNLcjkyelctVlRScmtTWXFYWG0xTWRpbG5uUVc1Q2JySW16bjFKYzBHM1hTWExDSFFzS1ZSLVhJazRBamxXS2ZodWhRMVUxV3Jub0VwblhCeFQ4RzZVUTY5SktnSi0wREJOMXYwNnRseTJYbWtZenBEUDhrUlRCeEk?oc=5\" target=\"_blank\"\u003eColombia earthquake: Buildings creaked, furniture shook - ‘It was a big scare’\u003c/a\u003e\u0026nbsp;\u0026nbsp;\u003cfont color=\"#6f6f6f\"\u003eMint\u003c/font\u003e\u003c/li\u003e\u003cli\u003e\u003ca href=\"https://news.google.com/rss/articles/CBMiqgFBVV95cUxQcnVqUXgtRnl4LWVfS2xmVk9GOV9HUkx1Z09rc0dLUGg5OWF0MGZpRnpaeTlXZEhVTVM3aFd0S2NjUldqakpDcWU4Z3QyM0hqaklxLUg3N0tCR3BjNVdfQ2JJUkRhTXcxY3FveWtQTEg1Vm43bjZFVThlOFpXVGhBUjhWWlZXTmMyaVRTSHZZbEdobU5ZM0N6cnBGZl9UUVA0ajhsMlFfYk9fdw?oc=5\" target=\"_blank\"\u003eMagnitude 6.5 earthquake strikes Colombia\u003c/a\u003e\u0026nbsp;\u0026nbsp;\u003cfont color=\"#6f6f6f\"\u003eReuters\u003c/font\u003e\u003c/li\u003e\u003c/ol\u003e",
         "link": "https://news.google.com/rss/articles/CBMieEFVX3lxTE5OYlZXSy1NNk95Vk5ETS1neHZ0YlRPZmFOOXNucUJCMDMyQkMwWFk4ZkgzNWE1Q1NzUHNJWmZmVGp6YzFmT0gyeC00Sk9QcmZOX0pldEJjbWczRExTRFJUVnFFQXdUd1AxT3p2bmZmV05uRW9QcDdTYdIBfkFVX3lxTE9hWUl1VkVadUV3U0swVTQtU09zXzBaX3BuWEVkQnlySk1TQ200UkdtYl9YSmx4TGFQeWw4OUdtZEo0dUlSenFEakhxNnhQT2RTZmt5RDJvNjVRNGprclVFV1BwTDFBY0daU3RGOHBQdlFKakpzbW13WnFMa0tGQQ?oc=5",
         "links": [
             "https://news.google.com/rss/articles/CBMieEFVX3lxTE5OYlZXSy1NNk95Vk5ETS1neHZ0YlRPZmFOOXNucUJCMDMyQkMwWFk4ZkgzNWE1Q1NzUHNJWmZmVGp6YzFmT0gyeC00Sk9QcmZOX0pldEJjbWczRExTRFJUVnFFQXdUd1AxT3p2bmZmV05uRW9QcDdTYdIBfkFVX3lxTE9hWUl1VkVadUV3U0swVTQtU09zXzBaX3BuWEVkQnlySk1TQ200UkdtYl9YSmx4TGFQeWw4OUdtZEo0dUlSenFEakhxNnhQT2RTZmt5RDJvNjVRNGprclVFV1BwTDFBY0daU3RGOHBQdlFKakpzbW13WnFMa0tGQQ?oc=5"
         ],
         "published": "Sun, 08 Jun 2025 18:06:54 GMT",
         "publishedParsed": "2025-06-08T18:06:54Z",
         "guid": "CBMieEFVX3lxTE5OYlZXSy1NNk95Vk5ETS1neHZ0YlRPZmFOOXNucUJCMDMyQkMwWFk4ZkgzNWE1Q1NzUHNJWmZmVGp6YzFmT0gyeC00Sk9QcmZOX0pldEJjbWczRExTRFJUVnFFQXdUd1AxT3p2bmZmV05uRW9QcDdTYdIBfkFVX3lxTE9hWUl1VkVadUV3U0swVTQtU09zXzBaX3BuWEVkQnlySk1TQ200UkdtYl9YSmx4TGFQeWw4OUdtZEo0dUlSenFEakhxNnhQT2RTZmt5RDJvNjVRNGprclVFV1BwTDFBY0daU3RGOHBQdlFKakpzbW13WnFMa0tGQQ"
     },
     {
         "title": "Tropical Storm Barbara strengthens off Mexico’s Pacific coast, bringing heavy rain - AP News",
         "description": "\u003col\u003e\u003cli\u003e\u003ca href=\"https://news.google.com/rss/articles/CBMilwFBVV95cUxNMDdsamNoSzRBdl9PMmFZZmpaMzA5VUdrcE81WnM0UHZuVTdOdzQ4ZHdVY01pUktJZ29tbnZYeFNtcmxOTjFyaUVRYmxtYTNQLS02V0UwNElMWnF2WlYzSDZVS25IMnNJNUFyZ1hFV1FpdnFvTkZEY1FySGYwYWVadE1Xa3ByQ3JKVk1ENDJ6aHNhREphRWdN?oc=5\" target=\"_blank\"\u003eTropical Storm Barbara strengthens off Mexico’s Pacific coast, bringing heavy rain\u003c/a\u003e\u0026nbsp;\u0026nbsp;\u003cfont color=\"#6f6f6f\"\u003eAP News\u003c/font\u003e\u003c/li\u003e\u003cli\u003e\u003ca href=\"https://news.google.com/rss/articles/CBMigAFBVV95cUxNYVg4WXhhNVFjTzdoMlNORm1ZUmlqeVhleWs5c3F1dko0dmVOVnBZVERQRFhJeXBDazIyMXkyRGJxbVhLUkVPUVo3TzgzQ2Uta19USmF6aFZ1ZFpMYURxTnBqajZHbHJRSi1PQld3UF8zUXZZT0prM3ZoVVB2MWY5UNIBhgFBVV95cUxPWk4zQ1U0UFNSOHRhc3FTWlNqMWN3UFA1RUdfb01DWlJFR3NWTVd3LXNXZXpzcWpqNVlGS052YTVtRE1ZU2M5Nk1JZVpXQjRwWEdYZXMtQklSdkIzdTh4Z0RaMVRiMHBPVklfN1BMUDJlYUZ1QlRxQ0tlNTFSZThvWmlXNEc5Zw?oc=5\" target=\"_blank\"\u003eTropical Storm Barbara forms off the southwestern coast of Mexico, expected to become a hurricane\u003c/a\u003e\u0026nbsp;\u0026nbsp;\u003cfont color=\"#6f6f6f\"\u003eCBS News\u003c/font\u003e\u003c/li\u003e\u003cli\u003e\u003ca href=\"https://news.google.com/rss/articles/CBMirAFBVV95cUxNTnowQmVQU0N2YlV6Q3dzbUFOa29ZMVVhWmxnUGVENmhUNWxTR0Q5N1M1TEl2ZW9xNXBWUzhjQ25JN0ZpazVrcUozWVBLOEl2NnJsRFhtbEM4azFuT2FIcU5lMEtaYlVHS29qWWZtRWxkVlZsMFAyODRYbzFCV1FvNGg2elpaVjhNdmxSNUxFRGZYWTNpaEFCTUlOV3VoeVBGaThoMjk1Ym9RVFpy0gGyAUFVX3lxTE5CNFZoYUIyVDNUQW1wMGVKZlFGZGFDdnFRWFdJRGI0RmZaeWpNcnB4UmV1ZXF0WlRkaE03YkJjTzdTTEUzdU1EcWkwOWFnZnk1dE5QQllDcnB2OHVzZU1vdFNDR0M5b1FhM0pWNU4xd0Fld2JiZXloQU56anFCZUtNTEdONks4YUJmVTVSR2hHN2Z4bUVzYUhsbTdDX2tGeHhzdVJqc3dDNDFQbVN0V1BMNGc?oc=5\" target=\"_blank\"\u003eTropical Storm Barbara strengthens off Mexico, expected to become hurricane\u003c/a\u003e\u0026nbsp;\u0026nbsp;\u003cfont color=\"#6f6f6f\"\u003eFOX8 WGHP\u003c/font\u003e\u003c/li\u003e\u003cli\u003e\u003ca href=\"https://news.google.com/rss/articles/CBMijgFBVV95cUxPZGowTmNMVmJtYmxkYmNGZTB1clRXdE80RXoxSDBaZldQX09CRW1ETlhwelVKSzhEdTBaUzZoOVhBVlJMOHNRQVM2S3F4REVZbDQzQllRaWJVTm16OVFrMXRXSThWX2xyRjd6Zk1ZRmhuaFhPZ1BtUXZKZkNGcWl3TlFnX3BNVk9iNDAyT0Nn0gGTAUFVX3lxTE9SMDlILVY0TmlZb1M5MHJyeTVYREp1UjJHR3l5SXhfazlpVVJzY1liUmlFaEtuSnlaTml5SlhoeTZUUWhqeHBLbkU4X1czc0FmVF95aGlmYjlrd2VJN0h2cWlqRmxoWWZoLThfeTVwYUc0TU1YQlZDOGs1QXZCV3hyeDBHUW5xaXdfM01pSmppZGRwcw?oc=5\" target=\"_blank\"\u003eTropical Storm Cosme forms in Eastern Pacific, likely to become hurricane this week\u003c/a\u003e\u0026nbsp;\u0026nbsp;\u003cfont color=\"#6f6f6f\"\u003eFOX Weather\u003c/font\u003e\u003c/li\u003e\u003cli\u003e\u003ca href=\"https://news.google.com/rss/articles/CBMimwFBVV95cUxQX1B5YzA0b3dHWkR2dlJHNFFubld0Z1Zaa09USnRYNjluTHBNVU9LU3RsOXczZzRrbDlyTENncHYzUGRiYTV5allHQkZJUGMybkdVSjZrR0xyaF9lSWU0blNPRWNpSVZiS3hRemVLanNMLXAteGdNclBIZmpFVmV4Qk4zS2tfOHU3TkNHcDNmLXRxQmhPZTZaMXBXQdIBoAFBVV95cUxNZHRUeUxnZWhaSGtnWGpQamtBX2RXMng2M3dVb3F3V0ZyUTlTTGNVMHA0V3FIM0pRYkdDdE5QRmVRaEtHOUFLTlNSMFlsSi1ia25LVWVaOE5nR09GM1V2VExFc1diMG1SRmYwbkd2b1ZRVUc2S1RWeFpwRTFSamVRamFyVEFscFhodGRmWEwzSkoxOEdvSVY2ZUhOS0NhTEZ1?oc=5\" target=\"_blank\"\u003eTropical Storm Barbara forms off southwest coast of Mexico\u003c/a\u003e\u0026nbsp;\u0026nbsp;\u003cfont color=\"#6f6f6f\"\u003ePBS\u003c/font\u003e\u003c/li\u003e\u003c/ol\u003e",
         "link": "https://news.google.com/rss/articles/CBMilwFBVV95cUxNMDdsamNoSzRBdl9PMmFZZmpaMzA5VUdrcE81WnM0UHZuVTdOdzQ4ZHdVY01pUktJZ29tbnZYeFNtcmxOTjFyaUVRYmxtYTNQLS02V0UwNElMWnF2WlYzSDZVS25IMnNJNUFyZ1hFV1FpdnFvTkZEY1FySGYwYWVadE1Xa3ByQ3JKVk1ENDJ6aHNhREphRWdN?oc=5",
         "links": [
             "https://news.google.com/rss/articles/CBMilwFBVV95cUxNMDdsamNoSzRBdl9PMmFZZmpaMzA5VUdrcE81WnM0UHZuVTdOdzQ4ZHdVY01pUktJZ29tbnZYeFNtcmxOTjFyaUVRYmxtYTNQLS02V0UwNElMWnF2WlYzSDZVS25IMnNJNUFyZ1hFV1FpdnFvTkZEY1FySGYwYWVadE1Xa3ByQ3JKVk1ENDJ6aHNhREphRWdN?oc=5"
         ],
         "published": "Mon, 09 Jun 2025 03:02:00 GMT",
         "publishedParsed": "2025-06-09T03:02:00Z",
         "guid": "CBMilwFBVV95cUxNMDdsamNoSzRBdl9PMmFZZmpaMzA5VUdrcE81WnM0UHZuVTdOdzQ4ZHdVY01pUktJZ29tbnZYeFNtcmxOTjFyaUVRYmxtYTNQLS02V0UwNElMWnF2WlYzSDZVS25IMnNJNUFyZ1hFV1FpdnFvTkZEY1FySGYwYWVadE1Xa3ByQ3JKVk1ENDJ6aHNhREphRWdN"
     },
     {
         "title": "A runaway pet zebra has been captured in Tennessee - NBC News",
         "description": "\u003col\u003e\u003cli\u003e\u003ca href=\"https://news.google.com/rss/articles/CBMijAFBVV95cUxNci01clBFamUxd0Y3S19SU2VrVmJpUk1nZVdkakxEbDJJT1dxRWxYSEdObDlOdmZyWEd0RUx1VGpzbmFUV1dOc2dRR0dHeW90aUtuRU9JcWFiRXFkb2V5SkZfVk42cTlVTzlMNnlSbFRCRER1NnExVVBnWnExSjNkNUI3UTFucDNsR283edIBVkFVX3lxTE1RaHhTa0FLcUF0NWZsbFI0NDFqM3VUOGZTU3hPYS1fV3d0OXd1R2hqVUtnSzUybG0yRFJFYUZRMWltNTF4XzdXejZiT3pNMThMS3JOZnp3?oc=5\" target=\"_blank\"\u003eA runaway pet zebra has been captured in Tennessee\u003c/a\u003e\u0026nbsp;\u0026nbsp;\u003cfont color=\"#6f6f6f\"\u003eNBC News\u003c/font\u003e\u003c/li\u003e\u003cli\u003e\u003ca href=\"https://news.google.com/rss/articles/CBMiekFVX3lxTE5DVGtwRU1WY2dDT0pTR29LWDZJOVdxcVlxdGNyMk0takxiMnp2V21iVzREdktrTzEtNDAxUU1FZ1dIWng2MXVJRWltTnVwZzBUenE3VVlHaHJqeS1tdThBUjRiRmxWaGkzMDJyUExVbExrS0dYV2tkZmpB?oc=5\" target=\"_blank\"\u003eRunaway Zebra Recaptured in a Tennessee County\u003c/a\u003e\u0026nbsp;\u0026nbsp;\u003cfont color=\"#6f6f6f\"\u003eThe New York Times\u003c/font\u003e\u003c/li\u003e\u003cli\u003e\u003ca href=\"https://news.google.com/rss/articles/CBMioAFBVV95cUxNbWx0bHlPS05uYU43RTItaGNrUUlnOWRZRGxzbTRXczRkdHRwM2Q0aU1OTHBxakRYWk5VbE1uSzVkeUFNQWJsR3Vpb1NGX3IzeVBPZVF3N3pkRTN2ZDU3S3ppWUdVNDV5STZmTGxOM0Z3dmlmWElVbUtpdUFPNERwMzh0RWdLaFZGdDVkY3dtb0VMUXRSdmk1czNaVWNXVGZS0gGmAUFVX3lxTE9tREJyaXNuM1A2WFBmMDN1MGFTUlNrTGdYZEM4eGhTcGZzZTcwYzVIU0w4dUQyVkFfMC0waGttNzJ4cVpTMndNRk5SQUJPYmx2Rk1HVW1xcnB5WmtoMldxVk9fWmxGY21udTRuejFpOE1IMVBpNHhkTFk2dFVrSWZxT0paVUp3NXY2SEw3RXlscXRBWnc4N2RVa19qQ1dNUV8zUV9NWmc?oc=5\" target=\"_blank\"\u003eRunaway zebra's wild adventure comes to an end after dramatic helicopter rescue\u003c/a\u003e\u0026nbsp;\u0026nbsp;\u003cfont color=\"#6f6f6f\"\u003eFox News\u003c/font\u003e\u003c/li\u003e\u003cli\u003e\u003ca href=\"https://news.google.com/rss/articles/CBMiqgFBVV95cUxNcnlIaFJCVUhrWEFReDdOdTJOSE1ScGV4Y1NQSWR0SkctdWdFZTc1U24tTzFySDNoaTJKVk5KM1J3Nk91VlNXeDI4TUxnZFNDOVVHUS1jYzI5XzJ4R0sya1F6TGU5dk9rOWRRMEhHeU4teEppalg0WF9JQkZSVDFlbnd4dEVfaTJqWHpBOFFtMVVLQUhwUzNZQ0hGemRxcXJvRS1ieHVFTlpNQQ?oc=5\" target=\"_blank\"\u003eAll the memes A to Zebra: How a missing animal in Tennessee inspired cakes, songs, more\u003c/a\u003e\u0026nbsp;\u0026nbsp;\u003cfont color=\"#6f6f6f\"\u003eThe Tennessean\u003c/font\u003e\u003c/li\u003e\u003cli\u003e\u003ca href=\"https://news.google.com/rss/articles/CBMiogFBVV95cUxNcTc1YUlnR08tNUxTSDdlaGw4XzdWeGRtVUpsekpuTXF2eF91WGQ5bnJ5UnlTZ0hBRl9veUxpMC1SQVN5Vm9XVVJrSGZkaER0MWpzY1VlQnhNRm5JOTZSQmRsSzlCRDBuZmtySHQyOUhpbDdrYTlJZ1JTYU1idV9xWmFUQ0RCV0stYk82dnlHRVlzTlVLZmpkRHA3cDFGdElxTkE?oc=5\" target=\"_blank\"\u003e‘He is safe’: Owners say missing zebra caught over a week after escaping\u003c/a\u003e\u0026nbsp;\u0026nbsp;\u003cfont color=\"#6f6f6f\"\u003eWSMV\u003c/font\u003e\u003c/li\u003e\u003c/ol\u003e",
         "link": "https://news.google.com/rss/articles/CBMijAFBVV95cUxNci01clBFamUxd0Y3S19SU2VrVmJpUk1nZVdkakxEbDJJT1dxRWxYSEdObDlOdmZyWEd0RUx1VGpzbmFUV1dOc2dRR0dHeW90aUtuRU9JcWFiRXFkb2V5SkZfVk42cTlVTzlMNnlSbFRCRER1NnExVVBnWnExSjNkNUI3UTFucDNsR283edIBVkFVX3lxTE1RaHhTa0FLcUF0NWZsbFI0NDFqM3VUOGZTU3hPYS1fV3d0OXd1R2hqVUtnSzUybG0yRFJFYUZRMWltNTF4XzdXejZiT3pNMThMS3JOZnp3?oc=5",
         "links": [
             "https://news.google.com/rss/articles/CBMijAFBVV95cUxNci01clBFamUxd0Y3S19SU2VrVmJpUk1nZVdkakxEbDJJT1dxRWxYSEdObDlOdmZyWEd0RUx1VGpzbmFUV1dOc2dRR0dHeW90aUtuRU9JcWFiRXFkb2V5SkZfVk42cTlVTzlMNnlSbFRCRER1NnExVVBnWnExSjNkNUI3UTFucDNsR283edIBVkFVX3lxTE1RaHhTa0FLcUF0NWZsbFI0NDFqM3VUOGZTU3hPYS1fV3d0OXd1R2hqVUtnSzUybG0yRFJFYUZRMWltNTF4XzdXejZiT3pNMThMS3JOZnp3?oc=5"
         ],
         "published": "Sun, 08 Jun 2025 19:56:32 GMT",
         "publishedParsed": "2025-06-08T19:56:32Z",
         "guid": "CBMijAFBVV95cUxNci01clBFamUxd0Y3S19SU2VrVmJpUk1nZVdkakxEbDJJT1dxRWxYSEdObDlOdmZyWEd0RUx1VGpzbmFUV1dOc2dRR0dHeW90aUtuRU9JcWFiRXFkb2V5SkZfVk42cTlVTzlMNnlSbFRCRER1NnExVVBnWnExSjNkNUI3UTFucDNsR283edIBVkFVX3lxTE1RaHhTa0FLcUF0NWZsbFI0NDFqM3VUOGZTU3hPYS1fV3d0OXd1R2hqVUtnSzUybG0yRFJFYUZRMWltNTF4XzdXejZiT3pNMThMS3JOZnp3"
     },
     {
         "title": "Skydiving plane crashed in Tullahoma near the airport - News Channel 5 Nashville",
         "description": "\u003col\u003e\u003cli\u003e\u003ca href=\"https://news.google.com/rss/articles/CBMifEFVX3lxTE5XVGpVWjhqZ2QtVGVqbWVVQ2NaZWpqQXhIendXT2s1VUhmRnJ1R09oOXJMemNUTHlsNDBVdV9WNEJDcDZ4QnpVZ19jZUJrY1l3NUxNRXVMN0tCeGItWVZLUVBxdms0ZUZINmdObHNmaEFmTm9HUjJmc1dBQ2o?oc=5\" target=\"_blank\"\u003eSkydiving plane crashed in Tullahoma near the airport\u003c/a\u003e\u0026nbsp;\u0026nbsp;\u003cfont color=\"#6f6f6f\"\u003eNews Channel 5 Nashville\u003c/font\u003e\u003c/li\u003e\u003cli\u003e\u003ca href=\"https://news.google.com/rss/articles/CBMijAFBVV95cUxPb043OFdSdHV1VzAzNVlCNXo0Ulo5Z05TMjlYeW1ESDVsX0VoTDRhcFhYRXJLbmpQaUJjTlQ2NHVlY0pGSUhHNDZJSDhnckdKTkdUTXo0RTRLY0hBUElyeDh2djUzZ2tIa1JvQjh0NUdzM09HOTQ4dzJsejl1Y2JlY19EUkpBT0tfMlpGLdIBkgFBVV95cUxNOUwtMlR3WmR1bDFNcUlRQVU1OFhtNDAydUlUWTQyazJ6SlFHc0c0dnoxNlFvcExTeHpVX1ZfV282SGFfUHczSkxpNUVBR0NwLXRwbmdWNUlUdlRYNTJMRkw3TG8zUHBOZEQxd2M4SEc5bGdVQnRfZzZVemo3eFd3Rm5oclYtTnhVbnNHaXhuMFo1dw?oc=5\" target=\"_blank\"\u003eSeveral injured after skydiving plane crashes in Tullahoma\u003c/a\u003e\u0026nbsp;\u0026nbsp;\u003cfont color=\"#6f6f6f\"\u003eWKRN News 2\u003c/font\u003e\u003c/li\u003e\u003cli\u003e\u003ca href=\"https://news.google.com/rss/articles/CBMieEFVX3lxTFB2cFVNeW1TbjZkQmtaZUlJdUZUcXZ3azVuWFRBbnJQakQzZlFWOHVnTGRLLUY2eXNoXzZJVHpJaUpBdkVaM2pjNFZuTHFfWHBSOXV3SGExMzVMRkhGd3ZHUFlZVWZXUjNrWDlaTHZXZjB0RlBVcURtcdIBfkFVX3lxTE1xTHgwbnBDZGF2VUx2OG1xZWhQNkt2R1FNbnFtU3lMZERKd243QU01Z0NTam1HYkQyQlZRZ3NlNzFZT3poM2J5dG9fdVl5TVZDWkxaM2M2LVlfbTFkVFlaQTNLRXpKWmdNWEd0blhHbHMtVHhwTkhPcWdtak1sdw?oc=5\" target=\"_blank\"\u003eNo fatalities reported after skydiving plane crashes in Tennessee, officials say\u003c/a\u003e\u0026nbsp;\u0026nbsp;\u003cfont color=\"#6f6f6f\"\u003eCNN\u003c/font\u003e\u003c/li\u003e\u003cli\u003e\u003ca href=\"https://news.google.com/rss/articles/CBMioAFBVV95cUxORXZQQURianB0ZHYzdE9NTHUxSzNQTmZJcW1NYVRzWUtiTjFQZFZEa1oyMjVBdnp1amtaQ0twUGRDMnlvaF9LNjlocjBPLTJ4Wm9wMXpOTDJkaEFFVzZNQzFONUNZbmlRaHQxb2pmQk9jMjBwMlR3eHBSbU9sUEVIbHM5c1dQTmZwZDlWZnZkdW5GZ1lwdVAwU3J3LVU5ZWRY?oc=5\" target=\"_blank\"\u003eFour hospitalized, multiple injured after plane crash in Coffee County\u003c/a\u003e\u0026nbsp;\u0026nbsp;\u003cfont color=\"#6f6f6f\"\u003eWSMV\u003c/font\u003e\u003c/li\u003e\u003cli\u003e\u003ca href=\"https://news.google.com/rss/articles/CBMiqwFBVV95cUxQcUhwUlJuV09tWnhIY1VyTDdqazd5d0p2dmJ6V1pnU3NfbzJKaEhIQkthdFFwNU9wT2IwaEtWeUpsNUYtT284ekQ1MWhMRGt2aG1MVTdkQ05tQktobTZhMktETF9CZzdESVZrS2JobUZNQWhvNS1ENzB5QTlXZ3dlTUt2dWJCWXlxZ291SjVWU0IxNTJDQXNfWnpjRzZvUjBUV0tyRFZfVlZ5dlE?oc=5\" target=\"_blank\"\u003eSkydiving Plane Carrying 20 People Crashes in Tennessee\u003c/a\u003e\u0026nbsp;\u0026nbsp;\u003cfont color=\"#6f6f6f\"\u003ePeople.com\u003c/font\u003e\u003c/li\u003e\u003c/ol\u003e",
         "link": "https://news.google.com/rss/articles/CBMifEFVX3lxTE5XVGpVWjhqZ2QtVGVqbWVVQ2NaZWpqQXhIendXT2s1VUhmRnJ1R09oOXJMemNUTHlsNDBVdV9WNEJDcDZ4QnpVZ19jZUJrY1l3NUxNRXVMN0tCeGItWVZLUVBxdms0ZUZINmdObHNmaEFmTm9HUjJmc1dBQ2o?oc=5",
         "links": [
             "https://news.google.com/rss/articles/CBMifEFVX3lxTE5XVGpVWjhqZ2QtVGVqbWVVQ2NaZWpqQXhIendXT2s1VUhmRnJ1R09oOXJMemNUTHlsNDBVdV9WNEJDcDZ4QnpVZ19jZUJrY1l3NUxNRXVMN0tCeGItWVZLUVBxdms0ZUZINmdObHNmaEFmTm9HUjJmc1dBQ2o?oc=5"
         ],
         "published": "Sun, 08 Jun 2025 18:41:44 GMT",
         "publishedParsed": "2025-06-08T18:41:44Z",
         "guid": "CBMifEFVX3lxTE5XVGpVWjhqZ2QtVGVqbWVVQ2NaZWpqQXhIendXT2s1VUhmRnJ1R09oOXJMemNUTHlsNDBVdV9WNEJDcDZ4QnpVZ19jZUJrY1l3NUxNRXVMN0tCeGItWVZLUVBxdms0ZUZINmdObHNmaEFmTm9HUjJmc1dBQ2o"
     },
     {
         "title": "FSE meets the FBI",
         "description": "\u003ca href=\"https://news.ycombinator.com/item?id=44220860\"\u003eComments\u003c/a\u003e",
         "link": "https://blog.freespeechextremist.com/blog/fse-vs-fbi.html",
         "links": [
             "https://blog.freespeechextremist.com/blog/fse-vs-fbi.html"
         ],
         "published": "Mon, 09 Jun 2025 01:59:27 +0000",
         "publishedParsed": "2025-06-09T01:59:27Z"
     },
     {
         "title": "Kagi Reaches 50k Users",
         "description": "\u003ca href=\"https://news.ycombinator.com/item?id=44221450\"\u003eComments\u003c/a\u003e",
         "link": "https://kagi.com/stats?stat=members",
         "links": [
             "https://kagi.com/stats?stat=members"
         ],
         "published": "Mon, 09 Jun 2025 04:38:32 +0000",
         "publishedParsed": "2025-06-09T04:38:32Z"
     },
     {
         "title": "Why Android can't use CDC Ethernet (2023)",
         "description": "\u003ca href=\"https://news.ycombinator.com/item?id=44219405\"\u003eComments\u003c/a\u003e",
         "link": "https://jordemort.dev/blog/why-android-cant-use-cdc-ethernet/",
         "links": [
             "https://jordemort.dev/blog/why-android-cant-use-cdc-ethernet/"
         ],
         "published": "Sun, 08 Jun 2025 20:49:07 +0000",
         "publishedParsed": "2025-06-08T20:49:07Z"
     },
     {
         "title": "Riding high in Germany on the world's oldest suspended railway",
         "description": "\u003ca href=\"https://news.ycombinator.com/item?id=44220179\"\u003eComments\u003c/a\u003e",
         "link": "https://www.theguardian.com/travel/2025/jun/09/riding-high-in-germany-on-the-worlds-oldest-suspended-railway",
         "links": [
             "https://www.theguardian.com/travel/2025/jun/09/riding-high-in-germany-on-the-worlds-oldest-suspended-railway"
         ],
         "published": "Sun, 08 Jun 2025 23:38:58 +0000",
         "publishedParsed": "2025-06-08T23:38:58Z"
     },
     {
         "title": "Zig Devlog: Self-Hosted x86 Back End Is Now Default in Debug Mode",
         "description": "\u003ca href=\"https://news.ycombinator.com/item?id=44219857\"\u003eComments\u003c/a\u003e",
         "link": "https://ziglang.org/devlog/2025/#2025-06-08",
         "links": [
             "https://ziglang.org/devlog/2025/#2025-06-08"
         ],
         "published": "Sun, 08 Jun 2025 22:24:14 +0000",
         "publishedParsed": "2025-06-08T22:24:14Z"
     },
     {
         "title": "Tracking Copilot vs. Codex vs. Cursor vs. Devin PR Performance",
         "description": "\u003ca href=\"https://news.ycombinator.com/item?id=44188839\"\u003eComments\u003c/a\u003e",
         "link": "https://aavetis.github.io/ai-pr-watcher/",
         "links": [
             "https://aavetis.github.io/ai-pr-watcher/"
         ],
         "published": "Thu, 05 Jun 2025 06:22:09 +0000",
         "publishedParsed": "2025-06-05T06:22:09Z"
     },
     {
         "title": "Omnimax",
         "description": "\u003ca href=\"https://news.ycombinator.com/item?id=44219357\"\u003eComments\u003c/a\u003e",
         "link": "https://computer.rip/2025-06-08-Omnimax.html",
         "links": [
             "https://computer.rip/2025-06-08-Omnimax.html"
         ],
         "published": "Sun, 08 Jun 2025 20:41:35 +0000",
         "publishedParsed": "2025-06-08T20:41:35Z"
     },
     {
         "title": "The wire that transforms much of Manhattan into one big, symbolic home (2017)",
         "description": "\u003ca href=\"https://news.ycombinator.com/item?id=44219270\"\u003eComments\u003c/a\u003e",
         "link": "https://www.atlasobscura.com/articles/eruv-manhattan-invisible-wire-jewish-symbolic-religious-home",
         "links": [
             "https://www.atlasobscura.com/articles/eruv-manhattan-invisible-wire-jewish-symbolic-religious-home"
         ],
         "published": "Sun, 08 Jun 2025 20:22:33 +0000",
         "publishedParsed": "2025-06-08T20:22:33Z"
     },
     {
         "title": "Administering immunotherapy in the morning seems to matter. Why?",
         "description": "\u003ca href=\"https://news.ycombinator.com/item?id=44217876\"\u003eComments\u003c/a\u003e",
         "link": "https://www.owlposting.com/p/the-time-of-day-that-immunotherapy",
         "links": [
             "https://www.owlposting.com/p/the-time-of-day-that-immunotherapy"
         ],
         "published": "Sun, 08 Jun 2025 16:18:32 +0000",
         "publishedParsed": "2025-06-08T16:18:32Z"
     },
     {
         "title": "Endangered classic Mac plastic color returns as 3D-printer filament",
         "description": "\u003ca href=\"https://news.ycombinator.com/item?id=44188373\"\u003eComments\u003c/a\u003e",
         "link": "https://arstechnica.com/apple/2025/06/new-filament-lets-you-3d-print-parts-in-authentic-1980s-apple-computer-color/",
         "links": [
             "https://arstechnica.com/apple/2025/06/new-filament-lets-you-3d-print-parts-in-authentic-1980s-apple-computer-color/"
         ],
         "published": "Thu, 05 Jun 2025 04:44:37 +0000",
         "publishedParsed": "2025-06-05T04:44:37Z"
     },
     {
         "title": "Analyzing IPv4 Trades with Gnuplot",
         "description": "\u003ca href=\"https://news.ycombinator.com/item?id=44220583\"\u003eComments\u003c/a\u003e",
         "link": "https://ipv4a-5539ad.gitlab.io/",
         "links": [
             "https://ipv4a-5539ad.gitlab.io/"
         ],
         "published": "Mon, 09 Jun 2025 01:08:00 +0000",
         "publishedParsed": "2025-06-09T01:08:00Z"
     },
     {
         "title": "My first attempt at iOS app development",
         "description": "\u003ca href=\"https://news.ycombinator.com/item?id=44188214\"\u003eComments\u003c/a\u003e",
         "link": "https://mgx.me/my-first-attempt-at-ios-app-development",
         "links": [
             "https://mgx.me/my-first-attempt-at-ios-app-development"
         ],
         "published": "Thu, 05 Jun 2025 04:02:04 +0000",
         "publishedParsed": "2025-06-05T04:02:04Z"
     },
     {
         "title": "Show HN: Let’s Bend – Open-Source Harmonica Bending Trainer",
         "description": "\u003ca href=\"https://news.ycombinator.com/item?id=44217757\"\u003eComments\u003c/a\u003e",
         "link": "https://letsbend.de",
         "links": [
             "https://letsbend.de"
         ],
         "published": "Sun, 08 Jun 2025 16:00:22 +0000",
         "publishedParsed": "2025-06-08T16:00:22Z"
     },
     {
         "title": "Gaussian integration is cool",
         "description": "\u003ca href=\"https://news.ycombinator.com/item?id=44215603\"\u003eComments\u003c/a\u003e",
         "link": "https://rohangautam.github.io/blog/chebyshev_gauss/",
         "links": [
             "https://rohangautam.github.io/blog/chebyshev_gauss/"
         ],
         "published": "Sun, 08 Jun 2025 08:35:54 +0000",
         "publishedParsed": "2025-06-08T08:35:54Z"
     },
     {
         "title": "Software Is About Promises",
         "description": "\u003ca href=\"https://news.ycombinator.com/item?id=44220287\"\u003eComments\u003c/a\u003e",
         "link": "https://www.bramadams.dev/software-is-about-promises/",
         "links": [
             "https://www.bramadams.dev/software-is-about-promises/"
         ],
         "published": "Mon, 09 Jun 2025 00:04:28 +0000",
         "publishedParsed": "2025-06-09T00:04:28Z"
     },
     {
         "title": "How to get started with writing tech video essays",
         "description": "\u003ca href=\"https://news.ycombinator.com/item?id=44189391\"\u003eComments\u003c/a\u003e",
         "link": "https://news.ycombinator.com/item?id=44189391",
         "links": [
             "https://news.ycombinator.com/item?id=44189391"
         ],
         "published": "Thu, 05 Jun 2025 07:53:14 +0000",
         "publishedParsed": "2025-06-05T07:53:14Z"
     },
     {
         "title": "Joining Apple Computer (2018)",
         "description": "\u003ca href=\"https://news.ycombinator.com/item?id=44212441\"\u003eComments\u003c/a\u003e",
         "link": "https://www.folklore.org/Joining_Apple_Computer.html",
         "links": [
             "https://www.folklore.org/Joining_Apple_Computer.html"
         ],
         "published": "Sat, 07 Jun 2025 20:32:54 +0000",
         "publishedParsed": "2025-06-07T20:32:54Z"
     },
     {
         "title": "How Compiler Explorer Works in 2025",
         "description": "\u003ca href=\"https://news.ycombinator.com/item?id=44183299\"\u003eComments\u003c/a\u003e",
         "link": "https://xania.org/202506/how-compiler-explorer-works",
         "links": [
             "https://xania.org/202506/how-compiler-explorer-works"
         ],
         "published": "Wed, 04 Jun 2025 17:32:34 +0000",
         "publishedParsed": "2025-06-04T17:32:34Z"
     },
     {
         "title": "Cheap yet ultrapure titanium might enable widespread use in industry (2024)",
         "description": "\u003ca href=\"https://news.ycombinator.com/item?id=44186008\"\u003eComments\u003c/a\u003e",
         "link": "https://phys.org/news/2024-06-cheap-ultrapure-titanium-metal-enable.amp",
         "links": [
             "https://phys.org/news/2024-06-cheap-ultrapure-titanium-metal-enable.amp"
         ],
         "published": "Wed, 04 Jun 2025 22:00:38 +0000",
         "publishedParsed": "2025-06-04T22:00:38Z"
     },
     {
         "title": "Poison everywhere: No output from your MCP server is safe",
         "description": "\u003ca href=\"https://news.ycombinator.com/item?id=44219755\"\u003eComments\u003c/a\u003e",
         "link": "https://www.cyberark.com/resources/threat-research-blog/poison-everywhere-no-output-from-your-mcp-server-is-safe",
         "links": [
             "https://www.cyberark.com/resources/threat-research-blog/poison-everywhere-no-output-from-your-mcp-server-is-safe"
         ],
         "published": "Sun, 08 Jun 2025 22:00:12 +0000",
         "publishedParsed": "2025-06-08T22:00:12Z"
     },
     {
         "title": "Building an AI server on a budget",
         "description": "\u003ca href=\"https://news.ycombinator.com/item?id=44197347\"\u003eComments\u003c/a\u003e",
         "link": "https://www.informationga.in/blog/building-an-ai-server-on-a-budget",
         "links": [
             "https://www.informationga.in/blog/building-an-ai-server-on-a-budget"
         ],
         "published": "Fri, 06 Jun 2025 02:33:16 +0000",
         "publishedParsed": "2025-06-06T02:33:16Z"
     },
     {
         "title": "Generating Pixels One by One",
         "description": "\u003ca href=\"https://news.ycombinator.com/item?id=44189088\"\u003eComments\u003c/a\u003e",
         "link": "https://tunahansalih.github.io/blog/autoregressive-vision-generation-part-1/",
         "links": [
             "https://tunahansalih.github.io/blog/autoregressive-vision-generation-part-1/"
         ],
         "published": "Thu, 05 Jun 2025 06:59:19 +0000",
         "publishedParsed": "2025-06-05T06:59:19Z"
     },
     {
         "title": "The last six months in LLMs, illustrated by pelicans on bicycles",
         "description": "\u003ca href=\"https://news.ycombinator.com/item?id=44215352\"\u003eComments\u003c/a\u003e",
         "link": "https://simonwillison.net/2025/Jun/6/six-months-in-llms/",
         "links": [
             "https://simonwillison.net/2025/Jun/6/six-months-in-llms/"
         ],
         "published": "Sun, 08 Jun 2025 07:38:37 +0000",
         "publishedParsed": "2025-06-08T07:38:37Z"
     },
     {
         "title": "Self-Host and Tech Independence: The Joy of Building Your Own",
         "description": "\u003ca href=\"https://news.ycombinator.com/item?id=44211273\"\u003eComments\u003c/a\u003e",
         "link": "https://www.ssp.sh/blog/self-host-self-independence/",
         "links": [
             "https://www.ssp.sh/blog/self-host-self-independence/"
         ],
         "published": "Sat, 07 Jun 2025 17:51:51 +0000",
         "publishedParsed": "2025-06-07T17:51:51Z"
     },
     {
         "title": "Binfmtc – binfmt_misc C scripting interface",
         "description": "\u003ca href=\"https://news.ycombinator.com/item?id=44216630\"\u003eComments\u003c/a\u003e",
         "link": "https://www.netfort.gr.jp/~dancer/software/binfmtc.html.en",
         "links": [
             "https://www.netfort.gr.jp/~dancer/software/binfmtc.html.en"
         ],
         "published": "Sun, 08 Jun 2025 12:38:55 +0000",
         "publishedParsed": "2025-06-08T12:38:55Z"
     },
     {
         "title": "I used AI-powered calorie counting apps, and they were even worse than expected",
         "description": "\u003ca href=\"https://news.ycombinator.com/item?id=44220135\"\u003eComments\u003c/a\u003e",
         "link": "https://lifehacker.com/health/ai-powered-calorie-counting-apps-worse-than-expected",
         "links": [
             "https://lifehacker.com/health/ai-powered-calorie-counting-apps-worse-than-expected"
         ],
         "published": "Sun, 08 Jun 2025 23:25:41 +0000",
         "publishedParsed": "2025-06-08T23:25:41Z"
     },
     {
         "title": "\u003cBlink\u003e and \u003cMarquee\u003e (2020)",
         "description": "\u003ca href=\"https://news.ycombinator.com/item?id=44214522\"\u003eComments\u003c/a\u003e",
         "link": "https://danq.me/2020/11/11/blink-and-marquee/",
         "links": [
             "https://danq.me/2020/11/11/blink-and-marquee/"
         ],
         "published": "Sun, 08 Jun 2025 04:17:43 +0000",
         "publishedParsed": "2025-06-08T04:17:43Z"
     },
     {
         "title": "FAA to eliminate floppy disks used in air traffic control systems",
         "description": "\u003ca href=\"https://news.ycombinator.com/item?id=44215197\"\u003eComments\u003c/a\u003e",
         "link": "https://www.tomshardware.com/pc-components/storage/the-faa-seeks-to-eliminate-floppy-disk-usage-in-air-traffic-control-systems",
         "links": [
             "https://www.tomshardware.com/pc-components/storage/the-faa-seeks-to-eliminate-floppy-disk-usage-in-air-traffic-control-systems"
         ],
         "published": "Sun, 08 Jun 2025 07:11:34 +0000",
         "publishedParsed": "2025-06-08T07:11:34Z"
     }
 ]